{"metrics": [{"reward_score": 30, "metric_time": 7486, "start_time": 6224, "elapsed_time_in_milliseconds": 1262, "episode": 1, "trial": 1, "phase": "training", "completion_percentage": 5, "episode_status": "Off track"}, {"reward_score": 28, "metric_time": 8748, "start_time": 7546, "elapsed_time_in_milliseconds": 1202, "episode": 2, "trial": 2, "phase": "training", "completion_percentage": 4, "episode_status": "Off track"}, {"reward_score": 56, "metric_time": 10488, "start_time": 8818, "elapsed_time_in_milliseconds": 1670, "episode": 3, "trial": 3, "phase": "training", "completion_percentage": 8, "episode_status": "Off track"}, {"reward_score": 40, "metric_time": 11760, "start_time": 10553, "elapsed_time_in_milliseconds": 1207, "episode": 4, "trial": 4, "phase": "training", "completion_percentage": 4, "episode_status": "Off track"}, {"reward_score": 64, "metric_time": 13823, "start_time": 11820, "elapsed_time_in_milliseconds": 2003, "episode": 5, "trial": 5, "phase": "training", "completion_percentage": 14, "episode_status": "Off track"}, {"reward_score": 134, "metric_time": 18289, "start_time": 13883, "elapsed_time_in_milliseconds": 4406, "episode": 6, "trial": 6, "phase": "training", "completion_percentage": 36, "episode_status": "Off track"}, {"reward_score": 146, "metric_time": 22219, "start_time": 18356, "elapsed_time_in_milliseconds": 3863, "episode": 7, "trial": 7, "phase": "training", "completion_percentage": 30, "episode_status": "Off track"}, {"reward_score": 80, "metric_time": 25414, "start_time": 22282, "elapsed_time_in_milliseconds": 3132, "episode": 8, "trial": 8, "phase": "training", "completion_percentage": 20, "episode_status": "Off track"}, {"reward_score": 70, "metric_time": 27691, "start_time": 25485, "elapsed_time_in_milliseconds": 2206, "episode": 9, "trial": 9, "phase": "training", "completion_percentage": 11, "episode_status": "Off track"}, {"reward_score": 84, "metric_time": 30765, "start_time": 27754, "elapsed_time_in_milliseconds": 3011, "episode": 10, "trial": 10, "phase": "training", "completion_percentage": 16, "episode_status": "Off track"}, {"reward_score": 67, "metric_time": 33085, "start_time": 30819, "elapsed_time_in_milliseconds": 2266, "episode": 11, "trial": 11, "phase": "training", "completion_percentage": 12, "episode_status": "Off track"}, {"reward_score": 54, "metric_time": 34887, "start_time": 33158, "elapsed_time_in_milliseconds": 1729, "episode": 12, "trial": 12, "phase": "training", "completion_percentage": 10, "episode_status": "Off track"}, {"reward_score": 42, "metric_time": 36423, "start_time": 34950, "elapsed_time_in_milliseconds": 1473, "episode": 13, "trial": 13, "phase": "training", "completion_percentage": 6, "episode_status": "Off track"}, {"reward_score": 41, "metric_time": 37954, "start_time": 36487, "elapsed_time_in_milliseconds": 1467, "episode": 14, "trial": 14, "phase": "training", "completion_percentage": 5, "episode_status": "Off track"}, {"reward_score": 18, "metric_time": 39091, "start_time": 38027, "elapsed_time_in_milliseconds": 1064, "episode": 15, "trial": 15, "phase": "training", "completion_percentage": 2, "episode_status": "Off track"}, {"reward_score": 39, "metric_time": 40416, "start_time": 39156, "elapsed_time_in_milliseconds": 1260, "episode": 16, "trial": 16, "phase": "training", "completion_percentage": 6, "episode_status": "Off track"}, {"reward_score": 26, "metric_time": 41560, "start_time": 40495, "elapsed_time_in_milliseconds": 1065, "episode": 17, "trial": 17, "phase": "training", "completion_percentage": 4, "episode_status": "Off track"}, {"reward_score": 47, "metric_time": 43221, "start_time": 41621, "elapsed_time_in_milliseconds": 1600, "episode": 18, "trial": 18, "phase": "training", "completion_percentage": 8, "episode_status": "Off track"}, {"reward_score": 72, "metric_time": 45887, "start_time": 43278, "elapsed_time_in_milliseconds": 2609, "episode": 19, "trial": 19, "phase": "training", "completion_percentage": 16, "episode_status": "Off track"}, {"reward_score": 23, "metric_time": 46954, "start_time": 45953, "elapsed_time_in_milliseconds": 1001, "episode": 20, "trial": 20, "phase": "training", "completion_percentage": 3, "episode_status": "Off track"}, {"reward_score": 99, "metric_time": 50289, "start_time": 47155, "elapsed_time_in_milliseconds": 3134, "episode": 20, "trial": 20, "phase": "evaluation", "completion_percentage": 19, "episode_status": "Off track"}, {"reward_score": 139, "metric_time": 53684, "start_time": 50357, "elapsed_time_in_milliseconds": 3327, "episode": 20, "trial": 20, "phase": "evaluation", "completion_percentage": 8, "episode_status": "Reversed"}, {"reward_score": 55, "metric_time": 55434, "start_time": 53749, "elapsed_time_in_milliseconds": 1685, "episode": 20, "trial": 20, "phase": "evaluation", "completion_percentage": 7, "episode_status": "Off track"}, {"reward_score": 53, "metric_time": 57153, "start_time": 55496, "elapsed_time_in_milliseconds": 1657, "episode": 20, "trial": 20, "phase": "evaluation", "completion_percentage": 7, "episode_status": "Off track"}, {"reward_score": 52, "metric_time": 58836, "start_time": 57225, "elapsed_time_in_milliseconds": 1611, "episode": 20, "trial": 20, "phase": "evaluation", "completion_percentage": 7, "episode_status": "Off track"}, {"reward_score": 31, "metric_time": 60025, "start_time": 58893, "elapsed_time_in_milliseconds": 1132, "episode": 21, "trial": 1, "phase": "training", "completion_percentage": 4, "episode_status": "Off track"}, {"reward_score": 28, "metric_time": 61160, "start_time": 60085, "elapsed_time_in_milliseconds": 1075, "episode": 22, "trial": 2, "phase": "training", "completion_percentage": 3, "episode_status": "Off track"}, {"reward_score": 59, "metric_time": 63089, "start_time": 61220, "elapsed_time_in_milliseconds": 1869, "episode": 23, "trial": 3, "phase": "training", "completion_percentage": 9, "episode_status": "Off track"}, {"reward_score": 80, "metric_time": 65487, "start_time": 63166, "elapsed_time_in_milliseconds": 2321, "episode": 24, "trial": 4, "phase": "training", "completion_percentage": 13, "episode_status": "Off track"}, {"reward_score": 67, "metric_time": 67878, "start_time": 65557, "elapsed_time_in_milliseconds": 2321, "episode": 25, "trial": 5, "phase": "training", "completion_percentage": 14, "episode_status": "Off track"}, {"reward_score": 59, "metric_time": 69762, "start_time": 67948, "elapsed_time_in_milliseconds": 1814, "episode": 26, "trial": 6, "phase": "training", "completion_percentage": 14, "episode_status": "Off track"}, {"reward_score": 115, "metric_time": 73287, "start_time": 69823, "elapsed_time_in_milliseconds": 3464, "episode": 27, "trial": 7, "phase": "training", "completion_percentage": 25, "episode_status": "Off track"}, {"reward_score": 45, "metric_time": 75025, "start_time": 73352, "elapsed_time_in_milliseconds": 1673, "episode": 28, "trial": 8, "phase": "training", "completion_percentage": 8, "episode_status": "Off track"}, {"reward_score": 38, "metric_time": 76413, "start_time": 75079, "elapsed_time_in_milliseconds": 1334, "episode": 29, "trial": 9, "phase": "training", "completion_percentage": 5, "episode_status": "Off track"}, {"reward_score": 85, "metric_time": 79495, "start_time": 76483, "elapsed_time_in_milliseconds": 3012, "episode": 30, "trial": 10, "phase": "training", "completion_percentage": 16, "episode_status": "Off track"}, {"reward_score": 53, "metric_time": 81425, "start_time": 79559, "elapsed_time_in_milliseconds": 1866, "episode": 31, "trial": 11, "phase": "training", "completion_percentage": 11, "episode_status": "Off track"}, {"reward_score": 107, "metric_time": 85155, "start_time": 81490, "elapsed_time_in_milliseconds": 3665, "episode": 32, "trial": 12, "phase": "training", "completion_percentage": 24, "episode_status": "Off track"}, {"reward_score": 94, "metric_time": 88231, "start_time": 85224, "elapsed_time_in_milliseconds": 3007, "episode": 33, "trial": 13, "phase": "training", "completion_percentage": 14, "episode_status": "Off track"}, {"reward_score": 49, "metric_time": 89825, "start_time": 88287, "elapsed_time_in_milliseconds": 1538, "episode": 34, "trial": 14, "phase": "training", "completion_percentage": 8, "episode_status": "Off track"}, {"reward_score": 73, "metric_time": 92292, "start_time": 89895, "elapsed_time_in_milliseconds": 2397, "episode": 35, "trial": 15, "phase": "training", "completion_percentage": 19, "episode_status": "Off track"}, {"reward_score": 40, "metric_time": 93692, "start_time": 92349, "elapsed_time_in_milliseconds": 1343, "episode": 36, "trial": 16, "phase": "training", "completion_percentage": 7, "episode_status": "Off track"}, {"reward_score": 119, "metric_time": 97625, "start_time": 93759, "elapsed_time_in_milliseconds": 3866, "episode": 37, "trial": 17, "phase": "training", "completion_percentage": 28, "episode_status": "Off track"}, {"reward_score": 38, "metric_time": 98820, "start_time": 97695, "elapsed_time_in_milliseconds": 1125, "episode": 38, "trial": 18, "phase": "training", "completion_percentage": 5, "episode_status": "Off track"}, {"reward_score": 22, "metric_time": 100159, "start_time": 98885, "elapsed_time_in_milliseconds": 1274, "episode": 39, "trial": 19, "phase": "training", "completion_percentage": 5, "episode_status": "Off track"}, {"reward_score": 58, "metric_time": 102165, "start_time": 100225, "elapsed_time_in_milliseconds": 1940, "episode": 40, "trial": 20, "phase": "training", "completion_percentage": 7, "episode_status": "Off track"}, {"reward_score": 54, "metric_time": 103892, "start_time": 102278, "elapsed_time_in_milliseconds": 1614, "episode": 40, "trial": 20, "phase": "evaluation", "completion_percentage": 9, "episode_status": "Off track"}, {"reward_score": 53, "metric_time": 105418, "start_time": 103961, "elapsed_time_in_milliseconds": 1457, "episode": 40, "trial": 20, "phase": "evaluation", "completion_percentage": 7, "episode_status": "Off track"}, {"reward_score": 80, "metric_time": 108429, "start_time": 105492, "elapsed_time_in_milliseconds": 2937, "episode": 40, "trial": 20, "phase": "evaluation", "completion_percentage": 25, "episode_status": "Off track"}, {"reward_score": 87, "metric_time": 111083, "start_time": 108491, "elapsed_time_in_milliseconds": 2592, "episode": 40, "trial": 20, "phase": "evaluation", "completion_percentage": 17, "episode_status": "Off track"}, {"reward_score": 54, "metric_time": 112826, "start_time": 111160, "elapsed_time_in_milliseconds": 1666, "episode": 40, "trial": 20, "phase": "evaluation", "completion_percentage": 9, "episode_status": "Off track"}, {"reward_score": 102, "metric_time": 115827, "start_time": 112889, "elapsed_time_in_milliseconds": 2938, "episode": 41, "trial": 1, "phase": "training", "completion_percentage": 19, "episode_status": "Off track"}, {"reward_score": 28, "metric_time": 117151, "start_time": 115897, "elapsed_time_in_milliseconds": 1254, "episode": 42, "trial": 2, "phase": "training", "completion_percentage": 3, "episode_status": "Off track"}, {"reward_score": 46, "metric_time": 118956, "start_time": 117221, "elapsed_time_in_milliseconds": 1735, "episode": 43, "trial": 3, "phase": "training", "completion_percentage": 9, "episode_status": "Off track"}, {"reward_score": 89, "metric_time": 121686, "start_time": 119020, "elapsed_time_in_milliseconds": 2666, "episode": 44, "trial": 4, "phase": "training", "completion_percentage": 23, "episode_status": "Off track"}, {"reward_score": 76, "metric_time": 123829, "start_time": 121757, "elapsed_time_in_milliseconds": 2072, "episode": 45, "trial": 5, "phase": "training", "completion_percentage": 19, "episode_status": "Off track"}, {"reward_score": 36, "metric_time": 125557, "start_time": 123880, "elapsed_time_in_milliseconds": 1677, "episode": 46, "trial": 6, "phase": "training", "completion_percentage": 9, "episode_status": "Off track"}, {"reward_score": 73, "metric_time": 128091, "start_time": 125622, "elapsed_time_in_milliseconds": 2469, "episode": 47, "trial": 7, "phase": "training", "completion_percentage": 14, "episode_status": "Off track"}, {"reward_score": 22, "metric_time": 129099, "start_time": 128153, "elapsed_time_in_milliseconds": 946, "episode": 48, "trial": 8, "phase": "training", "completion_percentage": 4, "episode_status": "Off track"}, {"reward_score": 34, "metric_time": 130366, "start_time": 129153, "elapsed_time_in_milliseconds": 1213, "episode": 49, "trial": 9, "phase": "training", "completion_percentage": 4, "episode_status": "Off track"}, {"reward_score": 82, "metric_time": 133095, "start_time": 130413, "elapsed_time_in_milliseconds": 2682, "episode": 50, "trial": 10, "phase": "training", "completion_percentage": 17, "episode_status": "Off track"}, {"reward_score": 76, "metric_time": 135368, "start_time": 133169, "elapsed_time_in_milliseconds": 2199, "episode": 51, "trial": 11, "phase": "training", "completion_percentage": 12, "episode_status": "Off track"}, {"reward_score": 49, "metric_time": 136959, "start_time": 135432, "elapsed_time_in_milliseconds": 1527, "episode": 52, "trial": 12, "phase": "training", "completion_percentage": 5, "episode_status": "Off track"}, {"reward_score": 64, "metric_time": 139228, "start_time": 137036, "elapsed_time_in_milliseconds": 2192, "episode": 53, "trial": 13, "phase": "training", "completion_percentage": 11, "episode_status": "Off track"}, {"reward_score": 83, "metric_time": 141828, "start_time": 139287, "elapsed_time_in_milliseconds": 2541, "episode": 54, "trial": 14, "phase": "training", "completion_percentage": 17, "episode_status": "Off track"}, {"reward_score": 47, "metric_time": 143566, "start_time": 141895, "elapsed_time_in_milliseconds": 1671, "episode": 55, "trial": 15, "phase": "training", "completion_percentage": 9, "episode_status": "Off track"}, {"reward_score": 143, "metric_time": 147290, "start_time": 143628, "elapsed_time_in_milliseconds": 3662, "episode": 56, "trial": 16, "phase": "training", "completion_percentage": 30, "episode_status": "Off track"}, {"reward_score": 44, "metric_time": 148829, "start_time": 147360, "elapsed_time_in_milliseconds": 1469, "episode": 57, "trial": 17, "phase": "training", "completion_percentage": 9, "episode_status": "Off track"}, {"reward_score": 116, "metric_time": 152287, "start_time": 148897, "elapsed_time_in_milliseconds": 3390, "episode": 58, "trial": 18, "phase": "training", "completion_percentage": 22, "episode_status": "Off track"}, {"reward_score": 197, "metric_time": 158159, "start_time": 152359, "elapsed_time_in_milliseconds": 5800, "episode": 59, "trial": 19, "phase": "training", "completion_percentage": 38, "episode_status": "Off track"}, {"reward_score": 98, "metric_time": 161492, "start_time": 158218, "elapsed_time_in_milliseconds": 3274, "episode": 60, "trial": 20, "phase": "training", "completion_percentage": 18, "episode_status": "Off track"}, {"reward_score": 52, "metric_time": 163231, "start_time": 161612, "elapsed_time_in_milliseconds": 1619, "episode": 60, "trial": 20, "phase": "evaluation", "completion_percentage": 9, "episode_status": "Off track"}, {"reward_score": 51, "metric_time": 164825, "start_time": 163290, "elapsed_time_in_milliseconds": 1535, "episode": 60, "trial": 20, "phase": "evaluation", "completion_percentage": 8, "episode_status": "Off track"}, {"reward_score": 50, "metric_time": 166435, "start_time": 164885, "elapsed_time_in_milliseconds": 1550, "episode": 60, "trial": 20, "phase": "evaluation", "completion_percentage": 9, "episode_status": "Off track"}, {"reward_score": 51, "metric_time": 168109, "start_time": 166485, "elapsed_time_in_milliseconds": 1624, "episode": 60, "trial": 20, "phase": "evaluation", "completion_percentage": 9, "episode_status": "Off track"}, {"reward_score": 46, "metric_time": 169703, "start_time": 168159, "elapsed_time_in_milliseconds": 1544, "episode": 60, "trial": 20, "phase": "evaluation", "completion_percentage": 8, "episode_status": "Off track"}, {"reward_score": 55, "metric_time": 171426, "start_time": 169754, "elapsed_time_in_milliseconds": 1672, "episode": 61, "trial": 1, "phase": "training", "completion_percentage": 9, "episode_status": "Off track"}, {"reward_score": 28, "metric_time": 172554, "start_time": 171504, "elapsed_time_in_milliseconds": 1050, "episode": 62, "trial": 2, "phase": "training", "completion_percentage": 3, "episode_status": "Off track"}, {"reward_score": 61, "metric_time": 174375, "start_time": 172629, "elapsed_time_in_milliseconds": 1746, "episode": 63, "trial": 3, "phase": "training", "completion_percentage": 9, "episode_status": "Off track"}, {"reward_score": 132, "metric_time": 178755, "start_time": 174422, "elapsed_time_in_milliseconds": 4333, "episode": 64, "trial": 4, "phase": "training", "completion_percentage": 37, "episode_status": "Off track"}, {"reward_score": 62, "metric_time": 180826, "start_time": 178823, "elapsed_time_in_milliseconds": 2003, "episode": 65, "trial": 5, "phase": "training", "completion_percentage": 13, "episode_status": "Off track"}, {"reward_score": 67, "metric_time": 183827, "start_time": 180885, "elapsed_time_in_milliseconds": 2942, "episode": 66, "trial": 6, "phase": "training", "completion_percentage": 25, "episode_status": "Off track"}, {"reward_score": 128, "metric_time": 187831, "start_time": 183894, "elapsed_time_in_milliseconds": 3937, "episode": 67, "trial": 7, "phase": "training", "completion_percentage": 28, "episode_status": "Off track"}, {"reward_score": 76, "metric_time": 190627, "start_time": 187904, "elapsed_time_in_milliseconds": 2723, "episode": 68, "trial": 8, "phase": "training", "completion_percentage": 15, "episode_status": "Off track"}, {"reward_score": 105, "metric_time": 193421, "start_time": 190694, "elapsed_time_in_milliseconds": 2727, "episode": 69, "trial": 9, "phase": "training", "completion_percentage": 20, "episode_status": "Off track"}, {"reward_score": 90, "metric_time": 196236, "start_time": 193482, "elapsed_time_in_milliseconds": 2754, "episode": 70, "trial": 10, "phase": "training", "completion_percentage": 18, "episode_status": "Off track"}, {"reward_score": 69, "metric_time": 198490, "start_time": 196293, "elapsed_time_in_milliseconds": 2197, "episode": 71, "trial": 11, "phase": "training", "completion_percentage": 10, "episode_status": "Off track"}, {"reward_score": 46, "metric_time": 200165, "start_time": 198565, "elapsed_time_in_milliseconds": 1600, "episode": 72, "trial": 12, "phase": "training", "completion_percentage": 6, "episode_status": "Off track"}, {"reward_score": 64, "metric_time": 202362, "start_time": 200227, "elapsed_time_in_milliseconds": 2135, "episode": 73, "trial": 13, "phase": "training", "completion_percentage": 10, "episode_status": "Off track"}, {"reward_score": 182, "metric_time": 207898, "start_time": 202424, "elapsed_time_in_milliseconds": 5474, "episode": 74, "trial": 14, "phase": "training", "completion_percentage": 42, "episode_status": "Off track"}, {"reward_score": 160, "metric_time": 212898, "start_time": 207958, "elapsed_time_in_milliseconds": 4940, "episode": 75, "trial": 15, "phase": "training", "completion_percentage": 37, "episode_status": "Off track"}, {"reward_score": 57, "metric_time": 215243, "start_time": 212953, "elapsed_time_in_milliseconds": 2290, "episode": 76, "trial": 16, "phase": "training", "completion_percentage": 16, "episode_status": "Off track"}, {"reward_score": 61, "metric_time": 217371, "start_time": 215293, "elapsed_time_in_milliseconds": 2078, "episode": 77, "trial": 17, "phase": "training", "completion_percentage": 13, "episode_status": "Off track"}, {"reward_score": 61, "metric_time": 219430, "start_time": 217427, "elapsed_time_in_milliseconds": 2003, "episode": 78, "trial": 18, "phase": "training", "completion_percentage": 11, "episode_status": "Off track"}, {"reward_score": 95, "metric_time": 222358, "start_time": 219501, "elapsed_time_in_milliseconds": 2857, "episode": 79, "trial": 19, "phase": "training", "completion_percentage": 17, "episode_status": "Off track"}, {"reward_score": 70, "metric_time": 224686, "start_time": 222424, "elapsed_time_in_milliseconds": 2262, "episode": 80, "trial": 20, "phase": "training", "completion_percentage": 11, "episode_status": "Off track"}, {"reward_score": 62, "metric_time": 226698, "start_time": 224823, "elapsed_time_in_milliseconds": 1875, "episode": 80, "trial": 20, "phase": "evaluation", "completion_percentage": 12, "episode_status": "Off track"}, {"reward_score": 64, "metric_time": 229033, "start_time": 226766, "elapsed_time_in_milliseconds": 2267, "episode": 80, "trial": 20, "phase": "evaluation", "completion_percentage": 14, "episode_status": "Off track"}, {"reward_score": 101, "metric_time": 232099, "start_time": 229108, "elapsed_time_in_milliseconds": 2991, "episode": 80, "trial": 20, "phase": "evaluation", "completion_percentage": 20, "episode_status": "Off track"}, {"reward_score": 105, "metric_time": 235572, "start_time": 232163, "elapsed_time_in_milliseconds": 3409, "episode": 80, "trial": 20, "phase": "evaluation", "completion_percentage": 19, "episode_status": "Off track"}, {"reward_score": 67, "metric_time": 237768, "start_time": 235626, "elapsed_time_in_milliseconds": 2142, "episode": 80, "trial": 20, "phase": "evaluation", "completion_percentage": 14, "episode_status": "Off track"}, {"reward_score": 85, "metric_time": 240769, "start_time": 237844, "elapsed_time_in_milliseconds": 2925, "episode": 81, "trial": 1, "phase": "training", "completion_percentage": 18, "episode_status": "Off track"}, {"reward_score": 27, "metric_time": 241904, "start_time": 240840, "elapsed_time_in_milliseconds": 1064, "episode": 82, "trial": 2, "phase": "training", "completion_percentage": 2, "episode_status": "Off track"}, {"reward_score": 44, "metric_time": 243563, "start_time": 241970, "elapsed_time_in_milliseconds": 1593, "episode": 83, "trial": 3, "phase": "training", "completion_percentage": 7, "episode_status": "Off track"}, {"reward_score": 36, "metric_time": 244979, "start_time": 243636, "elapsed_time_in_milliseconds": 1343, "episode": 84, "trial": 4, "phase": "training", "completion_percentage": 4, "episode_status": "Off track"}, {"reward_score": 65, "metric_time": 247313, "start_time": 245027, "elapsed_time_in_milliseconds": 2286, "episode": 85, "trial": 5, "phase": "training", "completion_percentage": 15, "episode_status": "Off track"}, {"reward_score": 19, "metric_time": 248228, "start_time": 247370, "elapsed_time_in_milliseconds": 858, "episode": 86, "trial": 6, "phase": "training", "completion_percentage": 4, "episode_status": "Off track"}, {"reward_score": 108, "metric_time": 251972, "start_time": 248309, "elapsed_time_in_milliseconds": 3663, "episode": 87, "trial": 7, "phase": "training", "completion_percentage": 26, "episode_status": "Off track"}, {"reward_score": 43, "metric_time": 253703, "start_time": 252030, "elapsed_time_in_milliseconds": 1673, "episode": 88, "trial": 8, "phase": "training", "completion_percentage": 9, "episode_status": "Off track"}, {"reward_score": 118, "metric_time": 256977, "start_time": 253771, "elapsed_time_in_milliseconds": 3206, "episode": 89, "trial": 9, "phase": "training", "completion_percentage": 20, "episode_status": "Off track"}, {"reward_score": 92, "metric_time": 259841, "start_time": 257032, "elapsed_time_in_milliseconds": 2809, "episode": 90, "trial": 10, "phase": "training", "completion_percentage": 15, "episode_status": "Off track"}, {"reward_score": 67, "metric_time": 261904, "start_time": 259909, "elapsed_time_in_milliseconds": 1995, "episode": 91, "trial": 11, "phase": "training", "completion_percentage": 10, "episode_status": "Off track"}, {"reward_score": 78, "metric_time": 264506, "start_time": 261973, "elapsed_time_in_milliseconds": 2533, "episode": 92, "trial": 12, "phase": "training", "completion_percentage": 15, "episode_status": "Off track"}, {"reward_score": 72, "metric_time": 267033, "start_time": 264569, "elapsed_time_in_milliseconds": 2464, "episode": 93, "trial": 13, "phase": "training", "completion_percentage": 11, "episode_status": "Off track"}, {"reward_score": 41, "metric_time": 268635, "start_time": 267103, "elapsed_time_in_milliseconds": 1532, "episode": 94, "trial": 14, "phase": "training", "completion_percentage": 5, "episode_status": "Off track"}, {"reward_score": 102, "metric_time": 271909, "start_time": 268699, "elapsed_time_in_milliseconds": 3210, "episode": 95, "trial": 15, "phase": "training", "completion_percentage": 27, "episode_status": "Off track"}, {"reward_score": 137, "metric_time": 276100, "start_time": 271968, "elapsed_time_in_milliseconds": 4132, "episode": 96, "trial": 16, "phase": "training", "completion_percentage": 31, "episode_status": "Off track"}, {"reward_score": 139, "metric_time": 280036, "start_time": 276166, "elapsed_time_in_milliseconds": 3870, "episode": 97, "trial": 17, "phase": "training", "completion_percentage": 28, "episode_status": "Off track"}, {"reward_score": 133, "metric_time": 284039, "start_time": 280110, "elapsed_time_in_milliseconds": 3929, "episode": 98, "trial": 18, "phase": "training", "completion_percentage": 22, "episode_status": "Off track"}, {"reward_score": 85, "metric_time": 286504, "start_time": 284105, "elapsed_time_in_milliseconds": 2399, "episode": 99, "trial": 19, "phase": "training", "completion_percentage": 16, "episode_status": "Off track"}, {"reward_score": 117, "metric_time": 290366, "start_time": 286570, "elapsed_time_in_milliseconds": 3796, "episode": 100, "trial": 20, "phase": "training", "completion_percentage": 22, "episode_status": "Off track"}, {"reward_score": 54, "metric_time": 292111, "start_time": 290493, "elapsed_time_in_milliseconds": 1618, "episode": 100, "trial": 20, "phase": "evaluation", "completion_percentage": 10, "episode_status": "Off track"}, {"reward_score": 98, "metric_time": 294791, "start_time": 292178, "elapsed_time_in_milliseconds": 2613, "episode": 100, "trial": 20, "phase": "evaluation", "completion_percentage": 18, "episode_status": "Off track"}, {"reward_score": 96, "metric_time": 297507, "start_time": 294830, "elapsed_time_in_milliseconds": 2677, "episode": 100, "trial": 20, "phase": "evaluation", "completion_percentage": 19, "episode_status": "Off track"}, {"reward_score": 48, "metric_time": 299178, "start_time": 297579, "elapsed_time_in_milliseconds": 1599, "episode": 100, "trial": 20, "phase": "evaluation", "completion_percentage": 8, "episode_status": "Off track"}, {"reward_score": 62, "metric_time": 301046, "start_time": 299247, "elapsed_time_in_milliseconds": 1799, "episode": 100, "trial": 20, "phase": "evaluation", "completion_percentage": 12, "episode_status": "Off track"}, {"reward_score": 52, "metric_time": 302773, "start_time": 301106, "elapsed_time_in_milliseconds": 1667, "episode": 101, "trial": 1, "phase": "training", "completion_percentage": 7, "episode_status": "Off track"}, {"reward_score": 118, "metric_time": 306831, "start_time": 302835, "elapsed_time_in_milliseconds": 3996, "episode": 102, "trial": 2, "phase": "training", "completion_percentage": 16, "episode_status": "Reversed"}, {"reward_score": 57, "metric_time": 308781, "start_time": 306903, "elapsed_time_in_milliseconds": 1878, "episode": 103, "trial": 3, "phase": "training", "completion_percentage": 9, "episode_status": "Off track"}, {"reward_score": 45, "metric_time": 310308, "start_time": 308836, "elapsed_time_in_milliseconds": 1472, "episode": 104, "trial": 4, "phase": "training", "completion_percentage": 5, "episode_status": "Off track"}, {"reward_score": 63, "metric_time": 312505, "start_time": 310375, "elapsed_time_in_milliseconds": 2130, "episode": 105, "trial": 5, "phase": "training", "completion_percentage": 15, "episode_status": "Off track"}, {"reward_score": 16, "metric_time": 313501, "start_time": 312576, "elapsed_time_in_milliseconds": 925, "episode": 106, "trial": 6, "phase": "training", "completion_percentage": 4, "episode_status": "Off track"}, {"reward_score": 128, "metric_time": 317522, "start_time": 313585, "elapsed_time_in_milliseconds": 3937, "episode": 107, "trial": 7, "phase": "training", "completion_percentage": 29, "episode_status": "Off track"}, {"reward_score": 56, "metric_time": 319444, "start_time": 317562, "elapsed_time_in_milliseconds": 1882, "episode": 108, "trial": 8, "phase": "training", "completion_percentage": 9, "episode_status": "Off track"}, {"reward_score": 100, "metric_time": 322446, "start_time": 319511, "elapsed_time_in_milliseconds": 2935, "episode": 109, "trial": 9, "phase": "training", "completion_percentage": 20, "episode_status": "Off track"}, {"reward_score": 67, "metric_time": 325118, "start_time": 322506, "elapsed_time_in_milliseconds": 2612, "episode": 110, "trial": 10, "phase": "training", "completion_percentage": 16, "episode_status": "Off track"}, {"reward_score": 73, "metric_time": 327582, "start_time": 325166, "elapsed_time_in_milliseconds": 2416, "episode": 111, "trial": 11, "phase": "training", "completion_percentage": 12, "episode_status": "Off track"}, {"reward_score": 112, "metric_time": 331179, "start_time": 327637, "elapsed_time_in_milliseconds": 3542, "episode": 112, "trial": 12, "phase": "training", "completion_percentage": 23, "episode_status": "Off track"}, {"reward_score": 200, "metric_time": 337634, "start_time": 331242, "elapsed_time_in_milliseconds": 6392, "episode": 113, "trial": 13, "phase": "training", "completion_percentage": 43, "episode_status": "Off track"}, {"reward_score": 143, "metric_time": 342637, "start_time": 337701, "elapsed_time_in_milliseconds": 4936, "episode": 114, "trial": 14, "phase": "training", "completion_percentage": 41, "episode_status": "Off track"}, {"reward_score": 160, "metric_time": 347372, "start_time": 342697, "elapsed_time_in_milliseconds": 4675, "episode": 115, "trial": 15, "phase": "training", "completion_percentage": 38, "episode_status": "Off track"}, {"reward_score": 155, "metric_time": 351836, "start_time": 347454, "elapsed_time_in_milliseconds": 4382, "episode": 116, "trial": 16, "phase": "training", "completion_percentage": 32, "episode_status": "Off track"}, {"reward_score": 121, "metric_time": 355585, "start_time": 351902, "elapsed_time_in_milliseconds": 3683, "episode": 117, "trial": 17, "phase": "training", "completion_percentage": 24, "episode_status": "Off track"}, {"reward_score": 120, "metric_time": 359299, "start_time": 355636, "elapsed_time_in_milliseconds": 3663, "episode": 118, "trial": 18, "phase": "training", "completion_percentage": 21, "episode_status": "Off track"}, {"reward_score": 213, "metric_time": 365690, "start_time": 359369, "elapsed_time_in_milliseconds": 6321, "episode": 119, "trial": 19, "phase": "training", "completion_percentage": 29, "episode_status": "Reversed"}, {"reward_score": 70, "metric_time": 368372, "start_time": 365764, "elapsed_time_in_milliseconds": 2608, "episode": 120, "trial": 20, "phase": "training", "completion_percentage": 12, "episode_status": "Off track"}, {"reward_score": 95, "metric_time": 371313, "start_time": 368496, "elapsed_time_in_milliseconds": 2817, "episode": 120, "trial": 20, "phase": "evaluation", "completion_percentage": 19, "episode_status": "Off track"}, {"reward_score": 95, "metric_time": 374254, "start_time": 371389, "elapsed_time_in_milliseconds": 2865, "episode": 120, "trial": 20, "phase": "evaluation", "completion_percentage": 18, "episode_status": "Off track"}, {"reward_score": 60, "metric_time": 376124, "start_time": 374312, "elapsed_time_in_milliseconds": 1812, "episode": 120, "trial": 20, "phase": "evaluation", "completion_percentage": 10, "episode_status": "Off track"}, {"reward_score": 111, "metric_time": 379511, "start_time": 376178, "elapsed_time_in_milliseconds": 3333, "episode": 120, "trial": 20, "phase": "evaluation", "completion_percentage": 19, "episode_status": "Off track"}, {"reward_score": 107, "metric_time": 382521, "start_time": 379595, "elapsed_time_in_milliseconds": 2926, "episode": 120, "trial": 20, "phase": "evaluation", "completion_percentage": 19, "episode_status": "Off track"}, {"reward_score": 96, "metric_time": 385518, "start_time": 382586, "elapsed_time_in_milliseconds": 2932, "episode": 121, "trial": 1, "phase": "training", "completion_percentage": 19, "episode_status": "Off track"}, {"reward_score": 82, "metric_time": 388251, "start_time": 385584, "elapsed_time_in_milliseconds": 2667, "episode": 122, "trial": 2, "phase": "training", "completion_percentage": 13, "episode_status": "Off track"}, {"reward_score": 115, "metric_time": 391908, "start_time": 388317, "elapsed_time_in_milliseconds": 3591, "episode": 123, "trial": 3, "phase": "training", "completion_percentage": 7, "episode_status": "Off track"}, {"reward_score": 83, "metric_time": 394458, "start_time": 391977, "elapsed_time_in_milliseconds": 2481, "episode": 124, "trial": 4, "phase": "training", "completion_percentage": 14, "episode_status": "Off track"}, {"reward_score": 60, "metric_time": 396520, "start_time": 394516, "elapsed_time_in_milliseconds": 2004, "episode": 125, "trial": 5, "phase": "training", "completion_percentage": 15, "episode_status": "Off track"}, {"reward_score": 58, "metric_time": 398185, "start_time": 396581, "elapsed_time_in_milliseconds": 1604, "episode": 126, "trial": 6, "phase": "training", "completion_percentage": 10, "episode_status": "Off track"}, {"reward_score": 144, "metric_time": 402653, "start_time": 398249, "elapsed_time_in_milliseconds": 4404, "episode": 127, "trial": 7, "phase": "training", "completion_percentage": 33, "episode_status": "Off track"}, {"reward_score": 364, "metric_time": 413792, "start_time": 402714, "elapsed_time_in_milliseconds": 11078, "episode": 128, "trial": 8, "phase": "training", "completion_percentage": 74, "episode_status": "Off track"}, {"reward_score": 43, "metric_time": 415318, "start_time": 413847, "elapsed_time_in_milliseconds": 1471, "episode": 129, "trial": 9, "phase": "training", "completion_percentage": 8, "episode_status": "Off track"}, {"reward_score": 75, "metric_time": 417384, "start_time": 415373, "elapsed_time_in_milliseconds": 2011, "episode": 130, "trial": 10, "phase": "training", "completion_percentage": 11, "episode_status": "Off track"}, {"reward_score": 75, "metric_time": 419788, "start_time": 417455, "elapsed_time_in_milliseconds": 2333, "episode": 131, "trial": 11, "phase": "training", "completion_percentage": 13, "episode_status": "Off track"}, {"reward_score": 49, "metric_time": 421446, "start_time": 419858, "elapsed_time_in_milliseconds": 1588, "episode": 132, "trial": 12, "phase": "training", "completion_percentage": 7, "episode_status": "Off track"}, {"reward_score": 78, "metric_time": 423785, "start_time": 421516, "elapsed_time_in_milliseconds": 2269, "episode": 133, "trial": 13, "phase": "training", "completion_percentage": 12, "episode_status": "Off track"}, {"reward_score": 41, "metric_time": 425512, "start_time": 423846, "elapsed_time_in_milliseconds": 1666, "episode": 134, "trial": 14, "phase": "training", "completion_percentage": 9, "episode_status": "Off track"}, {"reward_score": 40, "metric_time": 427185, "start_time": 425587, "elapsed_time_in_milliseconds": 1598, "episode": 135, "trial": 15, "phase": "training", "completion_percentage": 9, "episode_status": "Off track"}, {"reward_score": 92, "metric_time": 430120, "start_time": 427250, "elapsed_time_in_milliseconds": 2870, "episode": 136, "trial": 16, "phase": "training", "completion_percentage": 21, "episode_status": "Off track"}, {"reward_score": 146, "metric_time": 434593, "start_time": 430184, "elapsed_time_in_milliseconds": 4409, "episode": 137, "trial": 17, "phase": "training", "completion_percentage": 31, "episode_status": "Off track"}, {"reward_score": 119, "metric_time": 438315, "start_time": 434656, "elapsed_time_in_milliseconds": 3659, "episode": 138, "trial": 18, "phase": "training", "completion_percentage": 22, "episode_status": "Off track"}, {"reward_score": 89, "metric_time": 441522, "start_time": 438378, "elapsed_time_in_milliseconds": 3144, "episode": 139, "trial": 19, "phase": "training", "completion_percentage": 17, "episode_status": "Off track"}, {"reward_score": 80, "metric_time": 444326, "start_time": 441587, "elapsed_time_in_milliseconds": 2739, "episode": 140, "trial": 20, "phase": "training", "completion_percentage": 13, "episode_status": "Off track"}, {"reward_score": 97, "metric_time": 447319, "start_time": 444439, "elapsed_time_in_milliseconds": 2880, "episode": 140, "trial": 20, "phase": "evaluation", "completion_percentage": 19, "episode_status": "Off track"}, {"reward_score": 103, "metric_time": 450180, "start_time": 447400, "elapsed_time_in_milliseconds": 2780, "episode": 140, "trial": 20, "phase": "evaluation", "completion_percentage": 20, "episode_status": "Off track"}, {"reward_score": 90, "metric_time": 453197, "start_time": 450248, "elapsed_time_in_milliseconds": 2949, "episode": 140, "trial": 20, "phase": "evaluation", "completion_percentage": 18, "episode_status": "Off track"}, {"reward_score": 86, "metric_time": 455992, "start_time": 453242, "elapsed_time_in_milliseconds": 2750, "episode": 140, "trial": 20, "phase": "evaluation", "completion_percentage": 18, "episode_status": "Off track"}, {"reward_score": 220, "metric_time": 463212, "start_time": 456057, "elapsed_time_in_milliseconds": 7155, "episode": 140, "trial": 20, "phase": "evaluation", "completion_percentage": 58, "episode_status": "Off track"}, {"reward_score": 47, "metric_time": 464923, "start_time": 463249, "elapsed_time_in_milliseconds": 1674, "episode": 141, "trial": 1, "phase": "training", "completion_percentage": 8, "episode_status": "Off track"}, {"reward_score": 87, "metric_time": 467918, "start_time": 464981, "elapsed_time_in_milliseconds": 2937, "episode": 142, "trial": 2, "phase": "training", "completion_percentage": 15, "episode_status": "Off track"}, {"reward_score": 125, "metric_time": 472054, "start_time": 467990, "elapsed_time_in_milliseconds": 4064, "episode": 143, "trial": 3, "phase": "training", "completion_percentage": 28, "episode_status": "Off track"}, {"reward_score": 97, "metric_time": 475255, "start_time": 472118, "elapsed_time_in_milliseconds": 3137, "episode": 144, "trial": 4, "phase": "training", "completion_percentage": 21, "episode_status": "Off track"}, {"reward_score": 164, "metric_time": 480389, "start_time": 475321, "elapsed_time_in_milliseconds": 5068, "episode": 145, "trial": 5, "phase": "training", "completion_percentage": 41, "episode_status": "Off track"}, {"reward_score": 24, "metric_time": 481455, "start_time": 480459, "elapsed_time_in_milliseconds": 996, "episode": 146, "trial": 6, "phase": "training", "completion_percentage": 5, "episode_status": "Off track"}, {"reward_score": 73, "metric_time": 484189, "start_time": 481529, "elapsed_time_in_milliseconds": 2660, "episode": 147, "trial": 7, "phase": "training", "completion_percentage": 19, "episode_status": "Off track"}, {"reward_score": 44, "metric_time": 485985, "start_time": 484251, "elapsed_time_in_milliseconds": 1734, "episode": 148, "trial": 8, "phase": "training", "completion_percentage": 8, "episode_status": "Off track"}, {"reward_score": 260, "metric_time": 493589, "start_time": 486048, "elapsed_time_in_milliseconds": 7541, "episode": 149, "trial": 9, "phase": "training", "completion_percentage": 57, "episode_status": "Off track"}, {"reward_score": 57, "metric_time": 495591, "start_time": 493652, "elapsed_time_in_milliseconds": 1939, "episode": 150, "trial": 10, "phase": "training", "completion_percentage": 10, "episode_status": "Off track"}, {"reward_score": 33, "metric_time": 496847, "start_time": 495650, "elapsed_time_in_milliseconds": 1197, "episode": 151, "trial": 11, "phase": "training", "completion_percentage": 5, "episode_status": "Off track"}, {"reward_score": 74, "metric_time": 499326, "start_time": 496906, "elapsed_time_in_milliseconds": 2420, "episode": 152, "trial": 12, "phase": "training", "completion_percentage": 9, "episode_status": "Off track"}, {"reward_score": 87, "metric_time": 502451, "start_time": 499393, "elapsed_time_in_milliseconds": 3058, "episode": 153, "trial": 13, "phase": "training", "completion_percentage": 19, "episode_status": "Off track"}, {"reward_score": 49, "metric_time": 504591, "start_time": 502519, "elapsed_time_in_milliseconds": 2072, "episode": 154, "trial": 14, "phase": "training", "completion_percentage": 16, "episode_status": "Off track"}, {"reward_score": 66, "metric_time": 507372, "start_time": 504653, "elapsed_time_in_milliseconds": 2719, "episode": 155, "trial": 15, "phase": "training", "completion_percentage": 22, "episode_status": "Off track"}, {"reward_score": 76, "metric_time": 509766, "start_time": 507445, "elapsed_time_in_milliseconds": 2321, "episode": 156, "trial": 16, "phase": "training", "completion_percentage": 18, "episode_status": "Off track"}, {"reward_score": 139, "metric_time": 513983, "start_time": 509845, "elapsed_time_in_milliseconds": 4138, "episode": 157, "trial": 17, "phase": "training", "completion_percentage": 27, "episode_status": "Off track"}, {"reward_score": 30, "metric_time": 515188, "start_time": 514055, "elapsed_time_in_milliseconds": 1133, "episode": 158, "trial": 18, "phase": "training", "completion_percentage": 4, "episode_status": "Off track"}, {"reward_score": 78, "metric_time": 517786, "start_time": 515258, "elapsed_time_in_milliseconds": 2528, "episode": 159, "trial": 19, "phase": "training", "completion_percentage": 17, "episode_status": "Off track"}, {"reward_score": 65, "metric_time": 520190, "start_time": 517854, "elapsed_time_in_milliseconds": 2336, "episode": 160, "trial": 20, "phase": "training", "completion_percentage": 13, "episode_status": "Off track"}, {"reward_score": 75, "metric_time": 522663, "start_time": 520393, "elapsed_time_in_milliseconds": 2270, "episode": 160, "trial": 20, "phase": "evaluation", "completion_percentage": 12, "episode_status": "Off track"}, {"reward_score": 96, "metric_time": 525674, "start_time": 522726, "elapsed_time_in_milliseconds": 2948, "episode": 160, "trial": 20, "phase": "evaluation", "completion_percentage": 18, "episode_status": "Off track"}, {"reward_score": 191, "metric_time": 532058, "start_time": 525726, "elapsed_time_in_milliseconds": 6332, "episode": 160, "trial": 20, "phase": "evaluation", "completion_percentage": 44, "episode_status": "Off track"}, {"reward_score": 94, "metric_time": 535191, "start_time": 532126, "elapsed_time_in_milliseconds": 3065, "episode": 160, "trial": 20, "phase": "evaluation", "completion_percentage": 19, "episode_status": "Off track"}, {"reward_score": 50, "metric_time": 536996, "start_time": 535273, "elapsed_time_in_milliseconds": 1723, "episode": 160, "trial": 20, "phase": "evaluation", "completion_percentage": 9, "episode_status": "Off track"}, {"reward_score": 109, "metric_time": 540788, "start_time": 537067, "elapsed_time_in_milliseconds": 3721, "episode": 161, "trial": 1, "phase": "training", "completion_percentage": 20, "episode_status": "Off track"}, {"reward_score": 31, "metric_time": 541998, "start_time": 540862, "elapsed_time_in_milliseconds": 1136, "episode": 162, "trial": 2, "phase": "training", "completion_percentage": 3, "episode_status": "Off track"}, {"reward_score": 59, "metric_time": 544071, "start_time": 542062, "elapsed_time_in_milliseconds": 2009, "episode": 163, "trial": 3, "phase": "training", "completion_percentage": 8, "episode_status": "Off track"}, {"reward_score": 89, "metric_time": 546792, "start_time": 544127, "elapsed_time_in_milliseconds": 2665, "episode": 164, "trial": 4, "phase": "training", "completion_percentage": 22, "episode_status": "Off track"}, {"reward_score": 155, "metric_time": 551726, "start_time": 546855, "elapsed_time_in_milliseconds": 4871, "episode": 165, "trial": 5, "phase": "training", "completion_percentage": 44, "episode_status": "Off track"}, {"reward_score": 108, "metric_time": 555397, "start_time": 551800, "elapsed_time_in_milliseconds": 3597, "episode": 166, "trial": 6, "phase": "training", "completion_percentage": 29, "episode_status": "Off track"}, {"reward_score": 42, "metric_time": 556737, "start_time": 555465, "elapsed_time_in_milliseconds": 1272, "episode": 167, "trial": 7, "phase": "training", "completion_percentage": 5, "episode_status": "Off track"}, {"reward_score": 73, "metric_time": 559394, "start_time": 556800, "elapsed_time_in_milliseconds": 2594, "episode": 168, "trial": 8, "phase": "training", "completion_percentage": 16, "episode_status": "Off track"}, {"reward_score": 185, "metric_time": 564730, "start_time": 559465, "elapsed_time_in_milliseconds": 5265, "episode": 169, "trial": 9, "phase": "training", "completion_percentage": 31, "episode_status": "Off track"}, {"reward_score": 126, "metric_time": 568541, "start_time": 564796, "elapsed_time_in_milliseconds": 3745, "episode": 170, "trial": 10, "phase": "training", "completion_percentage": 21, "episode_status": "Off track"}, {"reward_score": 84, "metric_time": 571396, "start_time": 568599, "elapsed_time_in_milliseconds": 2797, "episode": 171, "trial": 11, "phase": "training", "completion_percentage": 17, "episode_status": "Off track"}, {"reward_score": 54, "metric_time": 573335, "start_time": 571459, "elapsed_time_in_milliseconds": 1876, "episode": 172, "trial": 12, "phase": "training", "completion_percentage": 11, "episode_status": "Off track"}, {"reward_score": 119, "metric_time": 577062, "start_time": 573398, "elapsed_time_in_milliseconds": 3664, "episode": 173, "trial": 13, "phase": "training", "completion_percentage": 25, "episode_status": "Off track"}, {"reward_score": 210, "metric_time": 582735, "start_time": 577128, "elapsed_time_in_milliseconds": 5607, "episode": 174, "trial": 14, "phase": "training", "completion_percentage": 43, "episode_status": "Off track"}, {"reward_score": 87, "metric_time": 585669, "start_time": 582792, "elapsed_time_in_milliseconds": 2877, "episode": 175, "trial": 15, "phase": "training", "completion_percentage": 18, "episode_status": "Off track"}, {"reward_score": 141, "metric_time": 590272, "start_time": 585736, "elapsed_time_in_milliseconds": 4536, "episode": 176, "trial": 16, "phase": "training", "completion_percentage": 33, "episode_status": "Off track"}, {"reward_score": 59, "metric_time": 592460, "start_time": 590343, "elapsed_time_in_milliseconds": 2117, "episode": 177, "trial": 17, "phase": "training", "completion_percentage": 11, "episode_status": "Off track"}, {"reward_score": 69, "metric_time": 594732, "start_time": 592532, "elapsed_time_in_milliseconds": 2200, "episode": 178, "trial": 18, "phase": "training", "completion_percentage": 14, "episode_status": "Off track"}, {"reward_score": 159, "metric_time": 599946, "start_time": 594798, "elapsed_time_in_milliseconds": 5148, "episode": 179, "trial": 19, "phase": "training", "completion_percentage": 33, "episode_status": "Off track"}, {"reward_score": 75, "metric_time": 602469, "start_time": 599998, "elapsed_time_in_milliseconds": 2471, "episode": 180, "trial": 20, "phase": "training", "completion_percentage": 13, "episode_status": "Off track"}, {"reward_score": 90, "metric_time": 605546, "start_time": 602586, "elapsed_time_in_milliseconds": 2960, "episode": 180, "trial": 20, "phase": "evaluation", "completion_percentage": 18, "episode_status": "Off track"}, {"reward_score": 80, "metric_time": 608201, "start_time": 605600, "elapsed_time_in_milliseconds": 2601, "episode": 180, "trial": 20, "phase": "evaluation", "completion_percentage": 16, "episode_status": "Off track"}, {"reward_score": 335, "metric_time": 617404, "start_time": 608267, "elapsed_time_in_milliseconds": 9137, "episode": 180, "trial": 20, "phase": "evaluation", "completion_percentage": 70, "episode_status": "Off track"}, {"reward_score": 152, "metric_time": 622616, "start_time": 617454, "elapsed_time_in_milliseconds": 5162, "episode": 180, "trial": 20, "phase": "evaluation", "completion_percentage": 39, "episode_status": "Off track"}, {"reward_score": 112, "metric_time": 625872, "start_time": 622667, "elapsed_time_in_milliseconds": 3205, "episode": 180, "trial": 20, "phase": "evaluation", "completion_percentage": 19, "episode_status": "Off track"}, {"reward_score": 159, "metric_time": 631082, "start_time": 625951, "elapsed_time_in_milliseconds": 5131, "episode": 181, "trial": 1, "phase": "training", "completion_percentage": 38, "episode_status": "Off track"}, {"reward_score": 78, "metric_time": 633811, "start_time": 631133, "elapsed_time_in_milliseconds": 2678, "episode": 182, "trial": 2, "phase": "training", "completion_percentage": 14, "episode_status": "Off track"}, {"reward_score": 499, "metric_time": 646936, "start_time": 633882, "elapsed_time_in_milliseconds": 13054, "episode": 183, "trial": 3, "phase": "training", "completion_percentage": 100, "episode_status": "Lap complete"}, {"reward_score": 22, "metric_time": 648272, "start_time": 646997, "elapsed_time_in_milliseconds": 1275, "episode": 184, "trial": 4, "phase": "training", "completion_percentage": 7, "episode_status": "Off track"}, {"reward_score": 198, "metric_time": 654337, "start_time": 648340, "elapsed_time_in_milliseconds": 5997, "episode": 185, "trial": 5, "phase": "training", "completion_percentage": 45, "episode_status": "Off track"}, {"reward_score": 43, "metric_time": 655810, "start_time": 654395, "elapsed_time_in_milliseconds": 1415, "episode": 186, "trial": 6, "phase": "training", "completion_percentage": 7, "episode_status": "Off track"}, {"reward_score": 374, "metric_time": 666938, "start_time": 655865, "elapsed_time_in_milliseconds": 11073, "episode": 187, "trial": 7, "phase": "training", "completion_percentage": 77, "episode_status": "Off track"}, {"reward_score": 66, "metric_time": 669399, "start_time": 667006, "elapsed_time_in_milliseconds": 2393, "episode": 188, "trial": 8, "phase": "training", "completion_percentage": 18, "episode_status": "Off track"}, {"reward_score": 78, "metric_time": 671999, "start_time": 669460, "elapsed_time_in_milliseconds": 2539, "episode": 189, "trial": 9, "phase": "training", "completion_percentage": 13, "episode_status": "Off track"}, {"reward_score": 122, "metric_time": 676009, "start_time": 672064, "elapsed_time_in_milliseconds": 3945, "episode": 190, "trial": 10, "phase": "training", "completion_percentage": 25, "episode_status": "Off track"}, {"reward_score": 66, "metric_time": 678331, "start_time": 676056, "elapsed_time_in_milliseconds": 2275, "episode": 191, "trial": 11, "phase": "training", "completion_percentage": 11, "episode_status": "Off track"}, {"reward_score": 113, "metric_time": 682200, "start_time": 678406, "elapsed_time_in_milliseconds": 3794, "episode": 192, "trial": 12, "phase": "training", "completion_percentage": 23, "episode_status": "Off track"}, {"reward_score": 250, "metric_time": 690276, "start_time": 682282, "elapsed_time_in_milliseconds": 7994, "episode": 193, "trial": 13, "phase": "training", "completion_percentage": 59, "episode_status": "Off track"}, {"reward_score": 65, "metric_time": 692810, "start_time": 690335, "elapsed_time_in_milliseconds": 2475, "episode": 194, "trial": 14, "phase": "training", "completion_percentage": 14, "episode_status": "Off track"}, {"reward_score": 155, "metric_time": 697796, "start_time": 692867, "elapsed_time_in_milliseconds": 4929, "episode": 195, "trial": 15, "phase": "training", "completion_percentage": 36, "episode_status": "Off track"}, {"reward_score": 158, "metric_time": 702665, "start_time": 697871, "elapsed_time_in_milliseconds": 4794, "episode": 196, "trial": 16, "phase": "training", "completion_percentage": 33, "episode_status": "Off track"}, {"reward_score": 142, "metric_time": 707061, "start_time": 702733, "elapsed_time_in_milliseconds": 4328, "episode": 197, "trial": 17, "phase": "training", "completion_percentage": 28, "episode_status": "Off track"}, {"reward_score": 116, "metric_time": 710459, "start_time": 707145, "elapsed_time_in_milliseconds": 3314, "episode": 198, "trial": 18, "phase": "training", "completion_percentage": 22, "episode_status": "Off track"}, {"reward_score": 88, "metric_time": 713944, "start_time": 710526, "elapsed_time_in_milliseconds": 3418, "episode": 199, "trial": 19, "phase": "training", "completion_percentage": 20, "episode_status": "Off track"}, {"reward_score": 50, "metric_time": 716273, "start_time": 714017, "elapsed_time_in_milliseconds": 2256, "episode": 200, "trial": 20, "phase": "training", "completion_percentage": 14, "episode_status": "Off track"}, {"reward_score": 134, "metric_time": 721024, "start_time": 716391, "elapsed_time_in_milliseconds": 4633, "episode": 200, "trial": 20, "phase": "evaluation", "completion_percentage": 28, "episode_status": "Off track"}, {"reward_score": 104, "metric_time": 724474, "start_time": 721067, "elapsed_time_in_milliseconds": 3407, "episode": 200, "trial": 20, "phase": "evaluation", "completion_percentage": 22, "episode_status": "Off track"}, {"reward_score": 167, "metric_time": 729409, "start_time": 724544, "elapsed_time_in_milliseconds": 4865, "episode": 200, "trial": 20, "phase": "evaluation", "completion_percentage": 15, "episode_status": "Reversed"}, {"reward_score": 56, "metric_time": 731222, "start_time": 729498, "elapsed_time_in_milliseconds": 1724, "episode": 200, "trial": 20, "phase": "evaluation", "completion_percentage": 10, "episode_status": "Off track"}, {"reward_score": 99, "metric_time": 734553, "start_time": 731289, "elapsed_time_in_milliseconds": 3264, "episode": 200, "trial": 20, "phase": "evaluation", "completion_percentage": 18, "episode_status": "Off track"}, {"reward_score": 40, "metric_time": 736154, "start_time": 734615, "elapsed_time_in_milliseconds": 1539, "episode": 201, "trial": 1, "phase": "training", "completion_percentage": 6, "episode_status": "Off track"}, {"reward_score": 72, "metric_time": 738823, "start_time": 736216, "elapsed_time_in_milliseconds": 2607, "episode": 202, "trial": 2, "phase": "training", "completion_percentage": 15, "episode_status": "Off track"}, {"reward_score": 64, "metric_time": 741022, "start_time": 738891, "elapsed_time_in_milliseconds": 2131, "episode": 203, "trial": 3, "phase": "training", "completion_percentage": 11, "episode_status": "Off track"}, {"reward_score": 223, "metric_time": 747753, "start_time": 741084, "elapsed_time_in_milliseconds": 6669, "episode": 204, "trial": 4, "phase": "training", "completion_percentage": 47, "episode_status": "Off track"}, {"reward_score": 73, "metric_time": 750084, "start_time": 747818, "elapsed_time_in_milliseconds": 2266, "episode": 205, "trial": 5, "phase": "training", "completion_percentage": 15, "episode_status": "Off track"}, {"reward_score": 110, "metric_time": 753283, "start_time": 750154, "elapsed_time_in_milliseconds": 3129, "episode": 206, "trial": 6, "phase": "training", "completion_percentage": 23, "episode_status": "Off track"}, {"reward_score": 334, "metric_time": 763090, "start_time": 753349, "elapsed_time_in_milliseconds": 9741, "episode": 207, "trial": 7, "phase": "training", "completion_percentage": 66, "episode_status": "Off track"}, {"reward_score": 350, "metric_time": 773404, "start_time": 763153, "elapsed_time_in_milliseconds": 10251, "episode": 208, "trial": 8, "phase": "training", "completion_percentage": 73, "episode_status": "Off track"}, {"reward_score": 164, "metric_time": 778478, "start_time": 773481, "elapsed_time_in_milliseconds": 4997, "episode": 209, "trial": 9, "phase": "training", "completion_percentage": 31, "episode_status": "Off track"}, {"reward_score": 141, "metric_time": 783012, "start_time": 778553, "elapsed_time_in_milliseconds": 4459, "episode": 210, "trial": 10, "phase": "training", "completion_percentage": 25, "episode_status": "Off track"}, {"reward_score": 76, "metric_time": 785357, "start_time": 783083, "elapsed_time_in_milliseconds": 2274, "episode": 211, "trial": 11, "phase": "training", "completion_percentage": 11, "episode_status": "Off track"}, {"reward_score": 132, "metric_time": 789819, "start_time": 785417, "elapsed_time_in_milliseconds": 4402, "episode": 212, "trial": 12, "phase": "training", "completion_percentage": 26, "episode_status": "Off track"}, {"reward_score": 60, "metric_time": 792027, "start_time": 789878, "elapsed_time_in_milliseconds": 2149, "episode": 213, "trial": 13, "phase": "training", "completion_percentage": 9, "episode_status": "Off track"}, {"reward_score": 38, "metric_time": 793885, "start_time": 792085, "elapsed_time_in_milliseconds": 1800, "episode": 214, "trial": 14, "phase": "training", "completion_percentage": 11, "episode_status": "Off track"}, {"reward_score": 191, "metric_time": 799611, "start_time": 793951, "elapsed_time_in_milliseconds": 5660, "episode": 215, "trial": 15, "phase": "training", "completion_percentage": 38, "episode_status": "Off track"}, {"reward_score": 168, "metric_time": 804818, "start_time": 799687, "elapsed_time_in_milliseconds": 5131, "episode": 216, "trial": 16, "phase": "training", "completion_percentage": 31, "episode_status": "Off track"}, {"reward_score": 173, "metric_time": 810022, "start_time": 804873, "elapsed_time_in_milliseconds": 5149, "episode": 217, "trial": 17, "phase": "training", "completion_percentage": 29, "episode_status": "Off track"}, {"reward_score": 118, "metric_time": 813752, "start_time": 810085, "elapsed_time_in_milliseconds": 3667, "episode": 218, "trial": 18, "phase": "training", "completion_percentage": 20, "episode_status": "Off track"}, {"reward_score": 151, "metric_time": 818684, "start_time": 813820, "elapsed_time_in_milliseconds": 4864, "episode": 219, "trial": 19, "phase": "training", "completion_percentage": 28, "episode_status": "Off track"}, {"reward_score": 175, "metric_time": 824162, "start_time": 818751, "elapsed_time_in_milliseconds": 5411, "episode": 220, "trial": 20, "phase": "training", "completion_percentage": 33, "episode_status": "Off track"}, {"reward_score": 86, "metric_time": 826897, "start_time": 824271, "elapsed_time_in_milliseconds": 2626, "episode": 220, "trial": 20, "phase": "evaluation", "completion_percentage": 13, "episode_status": "Off track"}, {"reward_score": 125, "metric_time": 831219, "start_time": 826950, "elapsed_time_in_milliseconds": 4269, "episode": 220, "trial": 20, "phase": "evaluation", "completion_percentage": 23, "episode_status": "Off track"}, {"reward_score": 48, "metric_time": 832893, "start_time": 831291, "elapsed_time_in_milliseconds": 1602, "episode": 220, "trial": 20, "phase": "evaluation", "completion_percentage": 8, "episode_status": "Off track"}, {"reward_score": 139, "metric_time": 837741, "start_time": 832958, "elapsed_time_in_milliseconds": 4783, "episode": 220, "trial": 20, "phase": "evaluation", "completion_percentage": 18, "episode_status": "Reversed"}, {"reward_score": 84, "metric_time": 840363, "start_time": 837808, "elapsed_time_in_milliseconds": 2555, "episode": 220, "trial": 20, "phase": "evaluation", "completion_percentage": 13, "episode_status": "Off track"}, {"reward_score": 39, "metric_time": 842306, "start_time": 840416, "elapsed_time_in_milliseconds": 1890, "episode": 221, "trial": 1, "phase": "training", "completion_percentage": 10, "episode_status": "Off track"}, {"reward_score": 152, "metric_time": 847698, "start_time": 842356, "elapsed_time_in_milliseconds": 5342, "episode": 222, "trial": 2, "phase": "training", "completion_percentage": 34, "episode_status": "Off track"}, {"reward_score": 61, "metric_time": 850220, "start_time": 847757, "elapsed_time_in_milliseconds": 2463, "episode": 223, "trial": 3, "phase": "training", "completion_percentage": 11, "episode_status": "Off track"}, {"reward_score": 61, "metric_time": 852358, "start_time": 850293, "elapsed_time_in_milliseconds": 2065, "episode": 224, "trial": 4, "phase": "training", "completion_percentage": 15, "episode_status": "Off track"}, {"reward_score": 36, "metric_time": 854016, "start_time": 852418, "elapsed_time_in_milliseconds": 1598, "episode": 225, "trial": 5, "phase": "training", "completion_percentage": 9, "episode_status": "Off track"}, {"reward_score": 30, "metric_time": 855485, "start_time": 854089, "elapsed_time_in_milliseconds": 1396, "episode": 226, "trial": 6, "phase": "training", "completion_percentage": 8, "episode_status": "Off track"}, {"reward_score": 43, "metric_time": 856965, "start_time": 855559, "elapsed_time_in_milliseconds": 1406, "episode": 227, "trial": 7, "phase": "training", "completion_percentage": 8, "episode_status": "Off track"}, {"reward_score": 145, "metric_time": 861366, "start_time": 857018, "elapsed_time_in_milliseconds": 4348, "episode": 228, "trial": 8, "phase": "training", "completion_percentage": 28, "episode_status": "Off track"}, {"reward_score": 171, "metric_time": 866691, "start_time": 861422, "elapsed_time_in_milliseconds": 5269, "episode": 229, "trial": 9, "phase": "training", "completion_percentage": 31, "episode_status": "Off track"}, {"reward_score": 386, "metric_time": 877957, "start_time": 866754, "elapsed_time_in_milliseconds": 11203, "episode": 230, "trial": 10, "phase": "training", "completion_percentage": 66, "episode_status": "Off track"}, {"reward_score": 86, "metric_time": 881287, "start_time": 878019, "elapsed_time_in_milliseconds": 3268, "episode": 231, "trial": 11, "phase": "training", "completion_percentage": 17, "episode_status": "Off track"}, {"reward_score": 86, "metric_time": 884294, "start_time": 881354, "elapsed_time_in_milliseconds": 2940, "episode": 232, "trial": 12, "phase": "training", "completion_percentage": 17, "episode_status": "Off track"}, {"reward_score": 213, "metric_time": 890814, "start_time": 884369, "elapsed_time_in_milliseconds": 6445, "episode": 233, "trial": 13, "phase": "training", "completion_percentage": 47, "episode_status": "Off track"}, {"reward_score": 23, "metric_time": 892423, "start_time": 890896, "elapsed_time_in_milliseconds": 1527, "episode": 234, "trial": 14, "phase": "training", "completion_percentage": 9, "episode_status": "Off track"}, {"reward_score": 281, "metric_time": 900554, "start_time": 892502, "elapsed_time_in_milliseconds": 8052, "episode": 235, "trial": 15, "phase": "training", "completion_percentage": 50, "episode_status": "Off track"}, {"reward_score": 203, "metric_time": 906634, "start_time": 900622, "elapsed_time_in_milliseconds": 6012, "episode": 236, "trial": 16, "phase": "training", "completion_percentage": 39, "episode_status": "Off track"}, {"reward_score": 66, "metric_time": 908959, "start_time": 906697, "elapsed_time_in_milliseconds": 2262, "episode": 237, "trial": 17, "phase": "training", "completion_percentage": 17, "episode_status": "Off track"}, {"reward_score": 233, "metric_time": 916034, "start_time": 909022, "elapsed_time_in_milliseconds": 7012, "episode": 238, "trial": 18, "phase": "training", "completion_percentage": 42, "episode_status": "Off track"}, {"reward_score": 108, "metric_time": 919900, "start_time": 916093, "elapsed_time_in_milliseconds": 3807, "episode": 239, "trial": 19, "phase": "training", "completion_percentage": 21, "episode_status": "Off track"}, {"reward_score": 78, "metric_time": 923029, "start_time": 919957, "elapsed_time_in_milliseconds": 3072, "episode": 240, "trial": 20, "phase": "training", "completion_percentage": 15, "episode_status": "Off track"}, {"reward_score": 144, "metric_time": 927441, "start_time": 923147, "elapsed_time_in_milliseconds": 4294, "episode": 240, "trial": 20, "phase": "evaluation", "completion_percentage": 27, "episode_status": "Off track"}, {"reward_score": 100, "metric_time": 931040, "start_time": 927480, "elapsed_time_in_milliseconds": 3560, "episode": 240, "trial": 20, "phase": "evaluation", "completion_percentage": 20, "episode_status": "Off track"}, {"reward_score": 118, "metric_time": 934374, "start_time": 931092, "elapsed_time_in_milliseconds": 3282, "episode": 240, "trial": 20, "phase": "evaluation", "completion_percentage": 19, "episode_status": "Off track"}, {"reward_score": 53, "metric_time": 935902, "start_time": 934417, "elapsed_time_in_milliseconds": 1485, "episode": 240, "trial": 20, "phase": "evaluation", "completion_percentage": 7, "episode_status": "Off track"}, {"reward_score": 298, "metric_time": 944510, "start_time": 935960, "elapsed_time_in_milliseconds": 8550, "episode": 240, "trial": 20, "phase": "evaluation", "completion_percentage": 61, "episode_status": "Off track"}, {"reward_score": 55, "metric_time": 946218, "start_time": 944552, "elapsed_time_in_milliseconds": 1666, "episode": 241, "trial": 1, "phase": "training", "completion_percentage": 7, "episode_status": "Off track"}, {"reward_score": 148, "metric_time": 950834, "start_time": 946302, "elapsed_time_in_milliseconds": 4532, "episode": 242, "trial": 2, "phase": "training", "completion_percentage": 29, "episode_status": "Off track"}, {"reward_score": 120, "metric_time": 954903, "start_time": 950905, "elapsed_time_in_milliseconds": 3998, "episode": 243, "trial": 3, "phase": "training", "completion_percentage": 26, "episode_status": "Off track"}, {"reward_score": 36, "metric_time": 956422, "start_time": 954970, "elapsed_time_in_milliseconds": 1452, "episode": 244, "trial": 4, "phase": "training", "completion_percentage": 10, "episode_status": "Off track"}, {"reward_score": 98, "metric_time": 959905, "start_time": 956502, "elapsed_time_in_milliseconds": 3403, "episode": 245, "trial": 5, "phase": "training", "completion_percentage": 28, "episode_status": "Off track"}, {"reward_score": 194, "metric_time": 966503, "start_time": 959979, "elapsed_time_in_milliseconds": 6524, "episode": 246, "trial": 6, "phase": "training", "completion_percentage": 47, "episode_status": "Off track"}, {"reward_score": 93, "metric_time": 969637, "start_time": 966565, "elapsed_time_in_milliseconds": 3072, "episode": 247, "trial": 7, "phase": "training", "completion_percentage": 20, "episode_status": "Off track"}, {"reward_score": 201, "metric_time": 975633, "start_time": 969701, "elapsed_time_in_milliseconds": 5932, "episode": 248, "trial": 8, "phase": "training", "completion_percentage": 35, "episode_status": "Off track"}, {"reward_score": 370, "metric_time": 986230, "start_time": 975701, "elapsed_time_in_milliseconds": 10529, "episode": 249, "trial": 9, "phase": "training", "completion_percentage": 73, "episode_status": "Off track"}, {"reward_score": 123, "metric_time": 990773, "start_time": 986307, "elapsed_time_in_milliseconds": 4466, "episode": 250, "trial": 10, "phase": "training", "completion_percentage": 25, "episode_status": "Off track"}, {"reward_score": 111, "metric_time": 994293, "start_time": 990819, "elapsed_time_in_milliseconds": 3474, "episode": 251, "trial": 11, "phase": "training", "completion_percentage": 19, "episode_status": "Off track"}, {"reward_score": 59, "metric_time": 996165, "start_time": 994367, "elapsed_time_in_milliseconds": 1798, "episode": 252, "trial": 12, "phase": "training", "completion_percentage": 10, "episode_status": "Off track"}, {"reward_score": 274, "metric_time": 1003970, "start_time": 996233, "elapsed_time_in_milliseconds": 7737, "episode": 253, "trial": 13, "phase": "training", "completion_percentage": 53, "episode_status": "Off track"}, {"reward_score": 115, "metric_time": 1007703, "start_time": 1004034, "elapsed_time_in_milliseconds": 3669, "episode": 254, "trial": 14, "phase": "training", "completion_percentage": 30, "episode_status": "Off track"}, {"reward_score": 254, "metric_time": 1015167, "start_time": 1007767, "elapsed_time_in_milliseconds": 7400, "episode": 255, "trial": 15, "phase": "training", "completion_percentage": 47, "episode_status": "Off track"}, {"reward_score": 360, "metric_time": 1025498, "start_time": 1015235, "elapsed_time_in_milliseconds": 10263, "episode": 256, "trial": 16, "phase": "training", "completion_percentage": 65, "episode_status": "Off track"}, {"reward_score": 132, "metric_time": 1029436, "start_time": 1025568, "elapsed_time_in_milliseconds": 3868, "episode": 257, "trial": 17, "phase": "training", "completion_percentage": 24, "episode_status": "Off track"}, {"reward_score": 181, "metric_time": 1035367, "start_time": 1029501, "elapsed_time_in_milliseconds": 5866, "episode": 258, "trial": 18, "phase": "training", "completion_percentage": 35, "episode_status": "Off track"}, {"reward_score": 105, "metric_time": 1038840, "start_time": 1035435, "elapsed_time_in_milliseconds": 3405, "episode": 259, "trial": 19, "phase": "training", "completion_percentage": 19, "episode_status": "Off track"}, {"reward_score": 154, "metric_time": 1043565, "start_time": 1038907, "elapsed_time_in_milliseconds": 4658, "episode": 260, "trial": 20, "phase": "training", "completion_percentage": 26, "episode_status": "Off track"}, {"reward_score": 63, "metric_time": 1045569, "start_time": 1043686, "elapsed_time_in_milliseconds": 1883, "episode": 260, "trial": 20, "phase": "evaluation", "completion_percentage": 11, "episode_status": "Off track"}, {"reward_score": 86, "metric_time": 1048309, "start_time": 1045642, "elapsed_time_in_milliseconds": 2667, "episode": 260, "trial": 20, "phase": "evaluation", "completion_percentage": 14, "episode_status": "Off track"}, {"reward_score": 60, "metric_time": 1050186, "start_time": 1048367, "elapsed_time_in_milliseconds": 1819, "episode": 260, "trial": 20, "phase": "evaluation", "completion_percentage": 10, "episode_status": "Off track"}, {"reward_score": 156, "metric_time": 1055244, "start_time": 1050240, "elapsed_time_in_milliseconds": 5004, "episode": 260, "trial": 20, "phase": "evaluation", "completion_percentage": 36, "episode_status": "Off track"}, {"reward_score": 58, "metric_time": 1056842, "start_time": 1055323, "elapsed_time_in_milliseconds": 1519, "episode": 260, "trial": 20, "phase": "evaluation", "completion_percentage": 7, "episode_status": "Off track"}, {"reward_score": 57, "metric_time": 1058646, "start_time": 1056910, "elapsed_time_in_milliseconds": 1736, "episode": 261, "trial": 1, "phase": "training", "completion_percentage": 7, "episode_status": "Off track"}, {"reward_score": 138, "metric_time": 1063706, "start_time": 1058704, "elapsed_time_in_milliseconds": 5002, "episode": 262, "trial": 2, "phase": "training", "completion_percentage": 32, "episode_status": "Off track"}, {"reward_score": 48, "metric_time": 1065442, "start_time": 1063779, "elapsed_time_in_milliseconds": 1663, "episode": 263, "trial": 3, "phase": "training", "completion_percentage": 8, "episode_status": "Off track"}, {"reward_score": 331, "metric_time": 1075643, "start_time": 1065506, "elapsed_time_in_milliseconds": 10137, "episode": 264, "trial": 4, "phase": "training", "completion_percentage": 66, "episode_status": "Off track"}, {"reward_score": 255, "metric_time": 1082980, "start_time": 1075692, "elapsed_time_in_milliseconds": 7288, "episode": 265, "trial": 5, "phase": "training", "completion_percentage": 53, "episode_status": "Off track"}, {"reward_score": 38, "metric_time": 1084645, "start_time": 1083044, "elapsed_time_in_milliseconds": 1601, "episode": 266, "trial": 6, "phase": "training", "completion_percentage": 11, "episode_status": "Off track"}, {"reward_score": 247, "metric_time": 1092523, "start_time": 1084708, "elapsed_time_in_milliseconds": 7815, "episode": 267, "trial": 7, "phase": "training", "completion_percentage": 41, "episode_status": "Off track"}, {"reward_score": 137, "metric_time": 1096714, "start_time": 1092580, "elapsed_time_in_milliseconds": 4134, "episode": 268, "trial": 8, "phase": "training", "completion_percentage": 25, "episode_status": "Off track"}, {"reward_score": 345, "metric_time": 1106119, "start_time": 1096783, "elapsed_time_in_milliseconds": 9336, "episode": 269, "trial": 9, "phase": "training", "completion_percentage": 71, "episode_status": "Off track"}, {"reward_score": 118, "metric_time": 1110377, "start_time": 1106170, "elapsed_time_in_milliseconds": 4207, "episode": 270, "trial": 10, "phase": "training", "completion_percentage": 21, "episode_status": "Off track"}, {"reward_score": 103, "metric_time": 1114573, "start_time": 1110439, "elapsed_time_in_milliseconds": 4134, "episode": 271, "trial": 11, "phase": "training", "completion_percentage": 23, "episode_status": "Off track"}, {"reward_score": 97, "metric_time": 1117783, "start_time": 1114640, "elapsed_time_in_milliseconds": 3143, "episode": 272, "trial": 12, "phase": "training", "completion_percentage": 17, "episode_status": "Off track"}, {"reward_score": 325, "metric_time": 1127511, "start_time": 1117839, "elapsed_time_in_milliseconds": 9672, "episode": 273, "trial": 13, "phase": "training", "completion_percentage": 62, "episode_status": "Off track"}, {"reward_score": 226, "metric_time": 1134917, "start_time": 1127586, "elapsed_time_in_milliseconds": 7331, "episode": 274, "trial": 14, "phase": "training", "completion_percentage": 55, "episode_status": "Off track"}, {"reward_score": 249, "metric_time": 1142659, "start_time": 1134969, "elapsed_time_in_milliseconds": 7690, "episode": 275, "trial": 15, "phase": "training", "completion_percentage": 48, "episode_status": "Off track"}, {"reward_score": 188, "metric_time": 1147970, "start_time": 1142705, "elapsed_time_in_milliseconds": 5265, "episode": 276, "trial": 16, "phase": "training", "completion_percentage": 32, "episode_status": "Off track"}, {"reward_score": 137, "metric_time": 1152179, "start_time": 1148033, "elapsed_time_in_milliseconds": 4146, "episode": 277, "trial": 17, "phase": "training", "completion_percentage": 27, "episode_status": "Off track"}, {"reward_score": 259, "metric_time": 1160109, "start_time": 1152243, "elapsed_time_in_milliseconds": 7866, "episode": 278, "trial": 18, "phase": "training", "completion_percentage": 44, "episode_status": "Off track"}, {"reward_score": 135, "metric_time": 1164441, "start_time": 1160173, "elapsed_time_in_milliseconds": 4268, "episode": 279, "trial": 19, "phase": "training", "completion_percentage": 22, "episode_status": "Off track"}, {"reward_score": 43, "metric_time": 1166447, "start_time": 1164514, "elapsed_time_in_milliseconds": 1933, "episode": 280, "trial": 20, "phase": "training", "completion_percentage": 10, "episode_status": "Off track"}, {"reward_score": 110, "metric_time": 1169835, "start_time": 1166565, "elapsed_time_in_milliseconds": 3270, "episode": 280, "trial": 20, "phase": "evaluation", "completion_percentage": 20, "episode_status": "Off track"}, {"reward_score": 83, "metric_time": 1172909, "start_time": 1169915, "elapsed_time_in_milliseconds": 2994, "episode": 280, "trial": 20, "phase": "evaluation", "completion_percentage": 9, "episode_status": "Off track"}, {"reward_score": 112, "metric_time": 1177248, "start_time": 1172962, "elapsed_time_in_milliseconds": 4286, "episode": 280, "trial": 20, "phase": "evaluation", "completion_percentage": 21, "episode_status": "Off track"}, {"reward_score": 119, "metric_time": 1180917, "start_time": 1177310, "elapsed_time_in_milliseconds": 3607, "episode": 280, "trial": 20, "phase": "evaluation", "completion_percentage": 21, "episode_status": "Off track"}, {"reward_score": 126, "metric_time": 1185248, "start_time": 1180977, "elapsed_time_in_milliseconds": 4271, "episode": 280, "trial": 20, "phase": "evaluation", "completion_percentage": 26, "episode_status": "Off track"}, {"reward_score": 105, "metric_time": 1189040, "start_time": 1185319, "elapsed_time_in_milliseconds": 3721, "episode": 281, "trial": 1, "phase": "training", "completion_percentage": 20, "episode_status": "Off track"}, {"reward_score": 97, "metric_time": 1192121, "start_time": 1189112, "elapsed_time_in_milliseconds": 3009, "episode": 282, "trial": 2, "phase": "training", "completion_percentage": 15, "episode_status": "Off track"}, {"reward_score": 297, "metric_time": 1200852, "start_time": 1192184, "elapsed_time_in_milliseconds": 8668, "episode": 283, "trial": 3, "phase": "training", "completion_percentage": 53, "episode_status": "Off track"}, {"reward_score": 505, "metric_time": 1214256, "start_time": 1200920, "elapsed_time_in_milliseconds": 13336, "episode": 284, "trial": 4, "phase": "training", "completion_percentage": 96, "episode_status": "Off track"}, {"reward_score": 374, "metric_time": 1225318, "start_time": 1214318, "elapsed_time_in_milliseconds": 11000, "episode": 285, "trial": 5, "phase": "training", "completion_percentage": 81, "episode_status": "Off track"}, {"reward_score": 222, "metric_time": 1232190, "start_time": 1225370, "elapsed_time_in_milliseconds": 6820, "episode": 286, "trial": 6, "phase": "training", "completion_percentage": 46, "episode_status": "Off track"}, {"reward_score": 64, "metric_time": 1234321, "start_time": 1232241, "elapsed_time_in_milliseconds": 2080, "episode": 287, "trial": 7, "phase": "training", "completion_percentage": 11, "episode_status": "Off track"}, {"reward_score": 147, "metric_time": 1239391, "start_time": 1234386, "elapsed_time_in_milliseconds": 5005, "episode": 288, "trial": 8, "phase": "training", "completion_percentage": 27, "episode_status": "Off track"}, {"reward_score": 166, "metric_time": 1245387, "start_time": 1239462, "elapsed_time_in_milliseconds": 5925, "episode": 289, "trial": 9, "phase": "training", "completion_percentage": 33, "episode_status": "Off track"}, {"reward_score": 198, "metric_time": 1252192, "start_time": 1245451, "elapsed_time_in_milliseconds": 6741, "episode": 290, "trial": 10, "phase": "training", "completion_percentage": 47, "episode_status": "Off track"}, {"reward_score": 481, "metric_time": 1265048, "start_time": 1252252, "elapsed_time_in_milliseconds": 12796, "episode": 291, "trial": 11, "phase": "training", "completion_percentage": 73, "episode_status": "Off track"}, {"reward_score": 202, "metric_time": 1271457, "start_time": 1265125, "elapsed_time_in_milliseconds": 6332, "episode": 292, "trial": 12, "phase": "training", "completion_percentage": 50, "episode_status": "Off track"}, {"reward_score": 90, "metric_time": 1274516, "start_time": 1271520, "elapsed_time_in_milliseconds": 2996, "episode": 293, "trial": 13, "phase": "training", "completion_percentage": 16, "episode_status": "Off track"}, {"reward_score": 271, "metric_time": 1281929, "start_time": 1274585, "elapsed_time_in_milliseconds": 7344, "episode": 294, "trial": 14, "phase": "training", "completion_percentage": 53, "episode_status": "Off track"}, {"reward_score": 212, "metric_time": 1288324, "start_time": 1281991, "elapsed_time_in_milliseconds": 6333, "episode": 295, "trial": 15, "phase": "training", "completion_percentage": 41, "episode_status": "Off track"}, {"reward_score": 196, "metric_time": 1293932, "start_time": 1288390, "elapsed_time_in_milliseconds": 5542, "episode": 296, "trial": 16, "phase": "training", "completion_percentage": 34, "episode_status": "Off track"}, {"reward_score": 158, "metric_time": 1298989, "start_time": 1293993, "elapsed_time_in_milliseconds": 4996, "episode": 297, "trial": 17, "phase": "training", "completion_percentage": 29, "episode_status": "Off track"}, {"reward_score": 146, "metric_time": 1303595, "start_time": 1299048, "elapsed_time_in_milliseconds": 4547, "episode": 298, "trial": 18, "phase": "training", "completion_percentage": 28, "episode_status": "Off track"}, {"reward_score": 202, "metric_time": 1309643, "start_time": 1303657, "elapsed_time_in_milliseconds": 5986, "episode": 299, "trial": 19, "phase": "training", "completion_percentage": 38, "episode_status": "Off track"}, {"reward_score": 123, "metric_time": 1313858, "start_time": 1309735, "elapsed_time_in_milliseconds": 4123, "episode": 300, "trial": 20, "phase": "training", "completion_percentage": 24, "episode_status": "Off track"}, {"reward_score": 546, "metric_time": 1328925, "start_time": 1313989, "elapsed_time_in_milliseconds": 14936, "episode": 300, "trial": 20, "phase": "evaluation", "completion_percentage": 100, "episode_status": "Lap complete"}, {"reward_score": 145, "metric_time": 1333582, "start_time": 1328991, "elapsed_time_in_milliseconds": 4591, "episode": 300, "trial": 20, "phase": "evaluation", "completion_percentage": 19, "episode_status": "Off track"}, {"reward_score": 106, "metric_time": 1337731, "start_time": 1333660, "elapsed_time_in_milliseconds": 4071, "episode": 300, "trial": 20, "phase": "evaluation", "completion_percentage": 28, "episode_status": "Off track"}, {"reward_score": 94, "metric_time": 1341057, "start_time": 1337805, "elapsed_time_in_milliseconds": 3252, "episode": 300, "trial": 20, "phase": "evaluation", "completion_percentage": 22, "episode_status": "Off track"}, {"reward_score": 552, "metric_time": 1355381, "start_time": 1341133, "elapsed_time_in_milliseconds": 14248, "episode": 300, "trial": 20, "phase": "evaluation", "completion_percentage": 100, "episode_status": "Lap complete"}, {"reward_score": 460, "metric_time": 1368469, "start_time": 1355465, "elapsed_time_in_milliseconds": 13004, "episode": 301, "trial": 1, "phase": "training", "completion_percentage": 88, "episode_status": "Off track"}, {"reward_score": 90, "metric_time": 1371865, "start_time": 1368518, "elapsed_time_in_milliseconds": 3347, "episode": 302, "trial": 2, "phase": "training", "completion_percentage": 16, "episode_status": "Off track"}, {"reward_score": 88, "metric_time": 1375398, "start_time": 1371924, "elapsed_time_in_milliseconds": 3474, "episode": 303, "trial": 3, "phase": "training", "completion_percentage": 19, "episode_status": "Off track"}, {"reward_score": 181, "metric_time": 1380937, "start_time": 1375463, "elapsed_time_in_milliseconds": 5474, "episode": 304, "trial": 4, "phase": "training", "completion_percentage": 30, "episode_status": "Off track"}, {"reward_score": 573, "metric_time": 1395203, "start_time": 1380991, "elapsed_time_in_milliseconds": 14212, "episode": 305, "trial": 5, "phase": "training", "completion_percentage": 100, "episode_status": "Lap complete"}, {"reward_score": 466, "metric_time": 1408524, "start_time": 1395272, "elapsed_time_in_milliseconds": 13252, "episode": 306, "trial": 6, "phase": "training", "completion_percentage": 85, "episode_status": "Off track"}, {"reward_score": 186, "metric_time": 1414396, "start_time": 1408598, "elapsed_time_in_milliseconds": 5798, "episode": 307, "trial": 7, "phase": "training", "completion_percentage": 31, "episode_status": "Off track"}, {"reward_score": 170, "metric_time": 1420054, "start_time": 1414473, "elapsed_time_in_milliseconds": 5581, "episode": 308, "trial": 8, "phase": "training", "completion_percentage": 37, "episode_status": "Off track"}, {"reward_score": 124, "metric_time": 1424395, "start_time": 1420136, "elapsed_time_in_milliseconds": 4259, "episode": 309, "trial": 9, "phase": "training", "completion_percentage": 22, "episode_status": "Off track"}, {"reward_score": 143, "metric_time": 1429328, "start_time": 1424465, "elapsed_time_in_milliseconds": 4863, "episode": 310, "trial": 10, "phase": "training", "completion_percentage": 29, "episode_status": "Off track"}, {"reward_score": 504, "metric_time": 1443065, "start_time": 1429394, "elapsed_time_in_milliseconds": 13671, "episode": 311, "trial": 11, "phase": "training", "completion_percentage": 91, "episode_status": "Off track"}, {"reward_score": 83, "metric_time": 1446063, "start_time": 1443128, "elapsed_time_in_milliseconds": 2935, "episode": 312, "trial": 12, "phase": "training", "completion_percentage": 15, "episode_status": "Off track"}, {"reward_score": 456, "metric_time": 1459130, "start_time": 1446129, "elapsed_time_in_milliseconds": 13001, "episode": 313, "trial": 13, "phase": "training", "completion_percentage": 93, "episode_status": "Off track"}, {"reward_score": 83, "metric_time": 1461924, "start_time": 1459200, "elapsed_time_in_milliseconds": 2724, "episode": 314, "trial": 14, "phase": "training", "completion_percentage": 15, "episode_status": "Off track"}, {"reward_score": 85, "metric_time": 1464734, "start_time": 1461998, "elapsed_time_in_milliseconds": 2736, "episode": 315, "trial": 15, "phase": "training", "completion_percentage": 16, "episode_status": "Off track"}, {"reward_score": 253, "metric_time": 1472333, "start_time": 1464796, "elapsed_time_in_milliseconds": 7537, "episode": 316, "trial": 16, "phase": "training", "completion_percentage": 44, "episode_status": "Off track"}, {"reward_score": 92, "metric_time": 1475529, "start_time": 1472397, "elapsed_time_in_milliseconds": 3132, "episode": 317, "trial": 17, "phase": "training", "completion_percentage": 20, "episode_status": "Off track"}, {"reward_score": 246, "metric_time": 1483395, "start_time": 1475594, "elapsed_time_in_milliseconds": 7801, "episode": 318, "trial": 18, "phase": "training", "completion_percentage": 41, "episode_status": "Off track"}, {"reward_score": 119, "metric_time": 1487526, "start_time": 1483465, "elapsed_time_in_milliseconds": 4061, "episode": 319, "trial": 19, "phase": "training", "completion_percentage": 23, "episode_status": "Off track"}, {"reward_score": 65, "metric_time": 1489865, "start_time": 1487593, "elapsed_time_in_milliseconds": 2272, "episode": 320, "trial": 20, "phase": "training", "completion_percentage": 12, "episode_status": "Off track"}, {"reward_score": 163, "metric_time": 1495267, "start_time": 1489989, "elapsed_time_in_milliseconds": 5278, "episode": 320, "trial": 20, "phase": "evaluation", "completion_percentage": 32, "episode_status": "Off track"}, {"reward_score": 453, "metric_time": 1508479, "start_time": 1495334, "elapsed_time_in_milliseconds": 13145, "episode": 320, "trial": 20, "phase": "evaluation", "completion_percentage": 86, "episode_status": "Off track"}, {"reward_score": 192, "metric_time": 1514990, "start_time": 1508595, "elapsed_time_in_milliseconds": 6395, "episode": 320, "trial": 20, "phase": "evaluation", "completion_percentage": 39, "episode_status": "Off track"}, {"reward_score": 134, "metric_time": 1519536, "start_time": 1515070, "elapsed_time_in_milliseconds": 4466, "episode": 320, "trial": 20, "phase": "evaluation", "completion_percentage": 25, "episode_status": "Off track"}, {"reward_score": 176, "metric_time": 1525538, "start_time": 1519662, "elapsed_time_in_milliseconds": 5876, "episode": 320, "trial": 20, "phase": "evaluation", "completion_percentage": 41, "episode_status": "Off track"}, {"reward_score": 169, "metric_time": 1530804, "start_time": 1525589, "elapsed_time_in_milliseconds": 5215, "episode": 321, "trial": 1, "phase": "training", "completion_percentage": 34, "episode_status": "Off track"}, {"reward_score": 158, "metric_time": 1535606, "start_time": 1530869, "elapsed_time_in_milliseconds": 4737, "episode": 322, "trial": 2, "phase": "training", "completion_percentage": 14, "episode_status": "Reversed"}, {"reward_score": 64, "metric_time": 1537944, "start_time": 1535670, "elapsed_time_in_milliseconds": 2274, "episode": 323, "trial": 3, "phase": "training", "completion_percentage": 10, "episode_status": "Off track"}, {"reward_score": 95, "metric_time": 1541269, "start_time": 1538002, "elapsed_time_in_milliseconds": 3267, "episode": 324, "trial": 4, "phase": "training", "completion_percentage": 22, "episode_status": "Off track"}, {"reward_score": 268, "metric_time": 1549741, "start_time": 1541345, "elapsed_time_in_milliseconds": 8396, "episode": 325, "trial": 5, "phase": "training", "completion_percentage": 63, "episode_status": "Off track"}, {"reward_score": 222, "metric_time": 1556743, "start_time": 1549802, "elapsed_time_in_milliseconds": 6941, "episode": 326, "trial": 6, "phase": "training", "completion_percentage": 50, "episode_status": "Off track"}, {"reward_score": 469, "metric_time": 1570253, "start_time": 1556804, "elapsed_time_in_milliseconds": 13449, "episode": 327, "trial": 7, "phase": "training", "completion_percentage": 91, "episode_status": "Off track"}, {"reward_score": 245, "metric_time": 1578543, "start_time": 1570351, "elapsed_time_in_milliseconds": 8192, "episode": 328, "trial": 8, "phase": "training", "completion_percentage": 48, "episode_status": "Off track"}, {"reward_score": 144, "metric_time": 1582933, "start_time": 1578611, "elapsed_time_in_milliseconds": 4322, "episode": 329, "trial": 9, "phase": "training", "completion_percentage": 22, "episode_status": "Off track"}, {"reward_score": 346, "metric_time": 1593073, "start_time": 1583019, "elapsed_time_in_milliseconds": 10054, "episode": 330, "trial": 10, "phase": "training", "completion_percentage": 62, "episode_status": "Off track"}, {"reward_score": 331, "metric_time": 1602752, "start_time": 1593130, "elapsed_time_in_milliseconds": 9622, "episode": 331, "trial": 11, "phase": "training", "completion_percentage": 62, "episode_status": "Off track"}, {"reward_score": 58, "metric_time": 1604675, "start_time": 1602795, "elapsed_time_in_milliseconds": 1880, "episode": 332, "trial": 12, "phase": "training", "completion_percentage": 8, "episode_status": "Off track"}, {"reward_score": 76, "metric_time": 1607070, "start_time": 1604752, "elapsed_time_in_milliseconds": 2318, "episode": 333, "trial": 13, "phase": "training", "completion_percentage": 11, "episode_status": "Off track"}, {"reward_score": 40, "metric_time": 1608600, "start_time": 1607134, "elapsed_time_in_milliseconds": 1466, "episode": 334, "trial": 14, "phase": "training", "completion_percentage": 5, "episode_status": "Off track"}, {"reward_score": 412, "metric_time": 1620343, "start_time": 1608674, "elapsed_time_in_milliseconds": 11669, "episode": 335, "trial": 15, "phase": "training", "completion_percentage": 68, "episode_status": "Off track"}, {"reward_score": 179, "metric_time": 1625800, "start_time": 1620407, "elapsed_time_in_milliseconds": 5393, "episode": 336, "trial": 16, "phase": "training", "completion_percentage": 33, "episode_status": "Off track"}, {"reward_score": 151, "metric_time": 1630545, "start_time": 1625872, "elapsed_time_in_milliseconds": 4673, "episode": 337, "trial": 17, "phase": "training", "completion_percentage": 27, "episode_status": "Off track"}, {"reward_score": 154, "metric_time": 1635873, "start_time": 1630613, "elapsed_time_in_milliseconds": 5260, "episode": 338, "trial": 18, "phase": "training", "completion_percentage": 31, "episode_status": "Off track"}, {"reward_score": 133, "metric_time": 1640486, "start_time": 1635949, "elapsed_time_in_milliseconds": 4537, "episode": 339, "trial": 19, "phase": "training", "completion_percentage": 24, "episode_status": "Off track"}, {"reward_score": 566, "metric_time": 1656351, "start_time": 1640534, "elapsed_time_in_milliseconds": 15817, "episode": 340, "trial": 20, "phase": "training", "completion_percentage": 100, "episode_status": "Lap complete"}, {"reward_score": 143, "metric_time": 1661218, "start_time": 1656457, "elapsed_time_in_milliseconds": 4761, "episode": 340, "trial": 20, "phase": "evaluation", "completion_percentage": 28, "episode_status": "Off track"}, {"reward_score": 183, "metric_time": 1666758, "start_time": 1661287, "elapsed_time_in_milliseconds": 5471, "episode": 340, "trial": 20, "phase": "evaluation", "completion_percentage": 35, "episode_status": "Off track"}, {"reward_score": 112, "metric_time": 1670621, "start_time": 1666808, "elapsed_time_in_milliseconds": 3813, "episode": 340, "trial": 20, "phase": "evaluation", "completion_percentage": 24, "episode_status": "Off track"}, {"reward_score": 119, "metric_time": 1674813, "start_time": 1670696, "elapsed_time_in_milliseconds": 4117, "episode": 340, "trial": 20, "phase": "evaluation", "completion_percentage": 24, "episode_status": "Off track"}, {"reward_score": 214, "metric_time": 1681419, "start_time": 1674875, "elapsed_time_in_milliseconds": 6544, "episode": 340, "trial": 20, "phase": "evaluation", "completion_percentage": 37, "episode_status": "Off track"}, {"reward_score": 441, "metric_time": 1694149, "start_time": 1681491, "elapsed_time_in_milliseconds": 12658, "episode": 341, "trial": 1, "phase": "training", "completion_percentage": 75, "episode_status": "Off track"}, {"reward_score": 153, "metric_time": 1699485, "start_time": 1694225, "elapsed_time_in_milliseconds": 5260, "episode": 342, "trial": 2, "phase": "training", "completion_percentage": 34, "episode_status": "Off track"}, {"reward_score": 563, "metric_time": 1715287, "start_time": 1699552, "elapsed_time_in_milliseconds": 15735, "episode": 343, "trial": 3, "phase": "training", "completion_percentage": 99, "episode_status": "Off track"}, {"reward_score": 58, "metric_time": 1717353, "start_time": 1715362, "elapsed_time_in_milliseconds": 1991, "episode": 344, "trial": 4, "phase": "training", "completion_percentage": 10, "episode_status": "Off track"}, {"reward_score": 73, "metric_time": 1720093, "start_time": 1717419, "elapsed_time_in_milliseconds": 2674, "episode": 345, "trial": 5, "phase": "training", "completion_percentage": 16, "episode_status": "Off track"}, {"reward_score": 570, "metric_time": 1735213, "start_time": 1720154, "elapsed_time_in_milliseconds": 15059, "episode": 346, "trial": 6, "phase": "training", "completion_percentage": 100, "episode_status": "Lap complete"}, {"reward_score": 181, "metric_time": 1740632, "start_time": 1735285, "elapsed_time_in_milliseconds": 5347, "episode": 347, "trial": 7, "phase": "training", "completion_percentage": 34, "episode_status": "Off track"}], "version": 2.0, "best_model_metric": "progress"}