{"metrics": [{"reward_score": 770, "metric_time": 20887, "start_time": 6430, "elapsed_time_in_milliseconds": 14457, "episode": 1, "trial": 1, "phase": "training", "completion_percentage": 100, "episode_status": "Lap complete"}, {"reward_score": 111, "metric_time": 23624, "start_time": 20958, "elapsed_time_in_milliseconds": 2666, "episode": 2, "trial": 2, "phase": "training", "completion_percentage": 15, "episode_status": "Off track"}, {"reward_score": 217, "metric_time": 28566, "start_time": 23692, "elapsed_time_in_milliseconds": 4874, "episode": 3, "trial": 3, "phase": "training", "completion_percentage": 29, "episode_status": "Off track"}, {"reward_score": 101, "metric_time": 31029, "start_time": 28628, "elapsed_time_in_milliseconds": 2401, "episode": 4, "trial": 4, "phase": "training", "completion_percentage": 15, "episode_status": "Off track"}, {"reward_score": 77, "metric_time": 33234, "start_time": 31089, "elapsed_time_in_milliseconds": 2145, "episode": 5, "trial": 5, "phase": "training", "completion_percentage": 11, "episode_status": "Off track"}, {"reward_score": 44, "metric_time": 34475, "start_time": 33286, "elapsed_time_in_milliseconds": 1189, "episode": 6, "trial": 6, "phase": "training", "completion_percentage": 3, "episode_status": "Off track"}, {"reward_score": 559, "metric_time": 46158, "start_time": 34546, "elapsed_time_in_milliseconds": 11612, "episode": 7, "trial": 7, "phase": "training", "completion_percentage": 79, "episode_status": "Off track"}, {"reward_score": 198, "metric_time": 50966, "start_time": 46218, "elapsed_time_in_milliseconds": 4748, "episode": 8, "trial": 8, "phase": "training", "completion_percentage": 28, "episode_status": "Off track"}, {"reward_score": 680, "metric_time": 64493, "start_time": 51020, "elapsed_time_in_milliseconds": 13473, "episode": 9, "trial": 9, "phase": "training", "completion_percentage": 80, "episode_status": "Off track"}, {"reward_score": 600, "metric_time": 77562, "start_time": 64551, "elapsed_time_in_milliseconds": 13011, "episode": 10, "trial": 10, "phase": "training", "completion_percentage": 78, "episode_status": "Off track"}, {"reward_score": 100, "metric_time": 80033, "start_time": 77624, "elapsed_time_in_milliseconds": 2409, "episode": 11, "trial": 11, "phase": "training", "completion_percentage": 11, "episode_status": "Off track"}, {"reward_score": 108, "metric_time": 82627, "start_time": 80083, "elapsed_time_in_milliseconds": 2544, "episode": 12, "trial": 12, "phase": "training", "completion_percentage": 15, "episode_status": "Off track"}, {"reward_score": 421, "metric_time": 91697, "start_time": 82690, "elapsed_time_in_milliseconds": 9007, "episode": 13, "trial": 13, "phase": "training", "completion_percentage": 58, "episode_status": "Off track"}, {"reward_score": 515, "metric_time": 103294, "start_time": 91761, "elapsed_time_in_milliseconds": 11533, "episode": 14, "trial": 14, "phase": "training", "completion_percentage": 69, "episode_status": "Off track"}, {"reward_score": 428, "metric_time": 112951, "start_time": 103363, "elapsed_time_in_milliseconds": 9588, "episode": 15, "trial": 15, "phase": "training", "completion_percentage": 68, "episode_status": "Off track"}, {"reward_score": 241, "metric_time": 118631, "start_time": 113029, "elapsed_time_in_milliseconds": 5602, "episode": 16, "trial": 16, "phase": "training", "completion_percentage": 31, "episode_status": "Off track"}, {"reward_score": 393, "metric_time": 127283, "start_time": 118697, "elapsed_time_in_milliseconds": 8586, "episode": 17, "trial": 17, "phase": "training", "completion_percentage": 53, "episode_status": "Off track"}, {"reward_score": 624, "metric_time": 140350, "start_time": 127352, "elapsed_time_in_milliseconds": 12998, "episode": 18, "trial": 18, "phase": "training", "completion_percentage": 86, "episode_status": "Off track"}, {"reward_score": 305, "metric_time": 147358, "start_time": 140416, "elapsed_time_in_milliseconds": 6942, "episode": 19, "trial": 19, "phase": "training", "completion_percentage": 39, "episode_status": "Off track"}, {"reward_score": 343, "metric_time": 154425, "start_time": 147418, "elapsed_time_in_milliseconds": 7007, "episode": 20, "trial": 20, "phase": "training", "completion_percentage": 42, "episode_status": "Off track"}, {"reward_score": 536, "metric_time": 166024, "start_time": 154587, "elapsed_time_in_milliseconds": 11437, "episode": 20, "trial": 20, "phase": "evaluation", "completion_percentage": 71, "episode_status": "Off track"}, {"reward_score": 213, "metric_time": 171561, "start_time": 166089, "elapsed_time_in_milliseconds": 5472, "episode": 20, "trial": 20, "phase": "evaluation", "completion_percentage": 34, "episode_status": "Off track"}, {"reward_score": 241, "metric_time": 177338, "start_time": 171630, "elapsed_time_in_milliseconds": 5708, "episode": 20, "trial": 20, "phase": "evaluation", "completion_percentage": 24, "episode_status": "Off track"}, {"reward_score": 72, "metric_time": 179690, "start_time": 177415, "elapsed_time_in_milliseconds": 2275, "episode": 20, "trial": 20, "phase": "evaluation", "completion_percentage": 14, "episode_status": "Off track"}, {"reward_score": 199, "metric_time": 184567, "start_time": 179754, "elapsed_time_in_milliseconds": 4813, "episode": 20, "trial": 20, "phase": "evaluation", "completion_percentage": 28, "episode_status": "Off track"}, {"reward_score": 235, "metric_time": 189961, "start_time": 184622, "elapsed_time_in_milliseconds": 5339, "episode": 21, "trial": 1, "phase": "training", "completion_percentage": 38, "episode_status": "Off track"}, {"reward_score": 161, "metric_time": 194295, "start_time": 190026, "elapsed_time_in_milliseconds": 4269, "episode": 22, "trial": 2, "phase": "training", "completion_percentage": 29, "episode_status": "Off track"}, {"reward_score": 195, "metric_time": 198759, "start_time": 194360, "elapsed_time_in_milliseconds": 4399, "episode": 23, "trial": 3, "phase": "training", "completion_percentage": 24, "episode_status": "Off track"}, {"reward_score": 113, "metric_time": 201756, "start_time": 198823, "elapsed_time_in_milliseconds": 2933, "episode": 24, "trial": 4, "phase": "training", "completion_percentage": 20, "episode_status": "Off track"}, {"reward_score": 851, "metric_time": 217827, "start_time": 201818, "elapsed_time_in_milliseconds": 16009, "episode": 25, "trial": 5, "phase": "training", "completion_percentage": 100, "episode_status": "Lap complete"}, {"reward_score": 123, "metric_time": 221221, "start_time": 217891, "elapsed_time_in_milliseconds": 3330, "episode": 26, "trial": 6, "phase": "training", "completion_percentage": 19, "episode_status": "Off track"}, {"reward_score": 78, "metric_time": 223359, "start_time": 221293, "elapsed_time_in_milliseconds": 2066, "episode": 27, "trial": 7, "phase": "training", "completion_percentage": 13, "episode_status": "Off track"}, {"reward_score": 235, "metric_time": 228568, "start_time": 223425, "elapsed_time_in_milliseconds": 5143, "episode": 28, "trial": 8, "phase": "training", "completion_percentage": 35, "episode_status": "Off track"}, {"reward_score": 742, "metric_time": 243629, "start_time": 228637, "elapsed_time_in_milliseconds": 14992, "episode": 29, "trial": 9, "phase": "training", "completion_percentage": 99, "episode_status": "Off track"}, {"reward_score": 128, "metric_time": 247031, "start_time": 243687, "elapsed_time_in_milliseconds": 3344, "episode": 30, "trial": 10, "phase": "training", "completion_percentage": 17, "episode_status": "Off track"}, {"reward_score": 99, "metric_time": 249759, "start_time": 247090, "elapsed_time_in_milliseconds": 2669, "episode": 31, "trial": 11, "phase": "training", "completion_percentage": 14, "episode_status": "Off track"}, {"reward_score": 316, "metric_time": 257221, "start_time": 249830, "elapsed_time_in_milliseconds": 7391, "episode": 32, "trial": 12, "phase": "training", "completion_percentage": 53, "episode_status": "Off track"}, {"reward_score": 182, "metric_time": 261205, "start_time": 257289, "elapsed_time_in_milliseconds": 3916, "episode": 33, "trial": 13, "phase": "training", "completion_percentage": 11, "episode_status": "Reversed"}, {"reward_score": 256, "metric_time": 267096, "start_time": 261268, "elapsed_time_in_milliseconds": 5828, "episode": 34, "trial": 14, "phase": "training", "completion_percentage": 33, "episode_status": "Off track"}, {"reward_score": 523, "metric_time": 277149, "start_time": 267161, "elapsed_time_in_milliseconds": 9988, "episode": 35, "trial": 15, "phase": "training", "completion_percentage": 48, "episode_status": "Reversed"}, {"reward_score": 184, "metric_time": 281422, "start_time": 277210, "elapsed_time_in_milliseconds": 4212, "episode": 36, "trial": 16, "phase": "training", "completion_percentage": 24, "episode_status": "Off track"}, {"reward_score": 486, "metric_time": 291827, "start_time": 281495, "elapsed_time_in_milliseconds": 10332, "episode": 37, "trial": 17, "phase": "training", "completion_percentage": 64, "episode_status": "Off track"}, {"reward_score": 305, "metric_time": 298568, "start_time": 291895, "elapsed_time_in_milliseconds": 6673, "episode": 38, "trial": 18, "phase": "training", "completion_percentage": 41, "episode_status": "Off track"}, {"reward_score": 823, "metric_time": 314161, "start_time": 298625, "elapsed_time_in_milliseconds": 15536, "episode": 39, "trial": 19, "phase": "training", "completion_percentage": 100, "episode_status": "Lap complete"}, {"reward_score": 143, "metric_time": 317760, "start_time": 314219, "elapsed_time_in_milliseconds": 3541, "episode": 40, "trial": 20, "phase": "training", "completion_percentage": 21, "episode_status": "Off track"}, {"reward_score": 204, "metric_time": 323104, "start_time": 317886, "elapsed_time_in_milliseconds": 5218, "episode": 40, "trial": 20, "phase": "evaluation", "completion_percentage": 31, "episode_status": "Off track"}, {"reward_score": 489, "metric_time": 333811, "start_time": 323160, "elapsed_time_in_milliseconds": 10651, "episode": 40, "trial": 20, "phase": "evaluation", "completion_percentage": 70, "episode_status": "Off track"}, {"reward_score": 219, "metric_time": 338766, "start_time": 333894, "elapsed_time_in_milliseconds": 4872, "episode": 40, "trial": 20, "phase": "evaluation", "completion_percentage": 34, "episode_status": "Off track"}, {"reward_score": 136, "metric_time": 341895, "start_time": 338836, "elapsed_time_in_milliseconds": 3059, "episode": 40, "trial": 20, "phase": "evaluation", "completion_percentage": 19, "episode_status": "Off track"}, {"reward_score": 220, "metric_time": 347296, "start_time": 341951, "elapsed_time_in_milliseconds": 5345, "episode": 40, "trial": 20, "phase": "evaluation", "completion_percentage": 35, "episode_status": "Off track"}, {"reward_score": 75, "metric_time": 349164, "start_time": 347356, "elapsed_time_in_milliseconds": 1808, "episode": 41, "trial": 1, "phase": "training", "completion_percentage": 10, "episode_status": "Off track"}, {"reward_score": 108, "metric_time": 352028, "start_time": 349215, "elapsed_time_in_milliseconds": 2813, "episode": 42, "trial": 2, "phase": "training", "completion_percentage": 17, "episode_status": "Off track"}, {"reward_score": 172, "metric_time": 355954, "start_time": 352091, "elapsed_time_in_milliseconds": 3863, "episode": 43, "trial": 3, "phase": "training", "completion_percentage": 21, "episode_status": "Off track"}, {"reward_score": 80, "metric_time": 358618, "start_time": 356017, "elapsed_time_in_milliseconds": 2601, "episode": 44, "trial": 4, "phase": "training", "completion_percentage": 17, "episode_status": "Off track"}, {"reward_score": 101, "metric_time": 361489, "start_time": 358692, "elapsed_time_in_milliseconds": 2797, "episode": 45, "trial": 5, "phase": "training", "completion_percentage": 19, "episode_status": "Off track"}, {"reward_score": 108, "metric_time": 364100, "start_time": 361553, "elapsed_time_in_milliseconds": 2547, "episode": 46, "trial": 6, "phase": "training", "completion_percentage": 13, "episode_status": "Off track"}, {"reward_score": 803, "metric_time": 378969, "start_time": 364162, "elapsed_time_in_milliseconds": 14807, "episode": 47, "trial": 7, "phase": "training", "completion_percentage": 99, "episode_status": "Off track"}, {"reward_score": 275, "metric_time": 385221, "start_time": 379024, "elapsed_time_in_milliseconds": 6197, "episode": 48, "trial": 8, "phase": "training", "completion_percentage": 34, "episode_status": "Off track"}, {"reward_score": 645, "metric_time": 397691, "start_time": 385287, "elapsed_time_in_milliseconds": 12404, "episode": 49, "trial": 9, "phase": "training", "completion_percentage": 83, "episode_status": "Off track"}, {"reward_score": 203, "metric_time": 403167, "start_time": 397752, "elapsed_time_in_milliseconds": 5415, "episode": 50, "trial": 10, "phase": "training", "completion_percentage": 34, "episode_status": "Off track"}, {"reward_score": 118, "metric_time": 406823, "start_time": 403227, "elapsed_time_in_milliseconds": 3596, "episode": 51, "trial": 11, "phase": "training", "completion_percentage": 24, "episode_status": "Off track"}, {"reward_score": 497, "metric_time": 418283, "start_time": 406885, "elapsed_time_in_milliseconds": 11398, "episode": 52, "trial": 12, "phase": "training", "completion_percentage": 70, "episode_status": "Off track"}, {"reward_score": 436, "metric_time": 427959, "start_time": 418340, "elapsed_time_in_milliseconds": 9619, "episode": 53, "trial": 13, "phase": "training", "completion_percentage": 60, "episode_status": "Off track"}, {"reward_score": 497, "metric_time": 438751, "start_time": 428019, "elapsed_time_in_milliseconds": 10732, "episode": 54, "trial": 14, "phase": "training", "completion_percentage": 62, "episode_status": "Off track"}, {"reward_score": 189, "metric_time": 443020, "start_time": 438815, "elapsed_time_in_milliseconds": 4205, "episode": 55, "trial": 15, "phase": "training", "completion_percentage": 26, "episode_status": "Off track"}, {"reward_score": 237, "metric_time": 448356, "start_time": 443079, "elapsed_time_in_milliseconds": 5277, "episode": 56, "trial": 16, "phase": "training", "completion_percentage": 35, "episode_status": "Off track"}, {"reward_score": 255, "metric_time": 454569, "start_time": 448423, "elapsed_time_in_milliseconds": 6146, "episode": 57, "trial": 17, "phase": "training", "completion_percentage": 38, "episode_status": "Off track"}, {"reward_score": 122, "metric_time": 457622, "start_time": 454620, "elapsed_time_in_milliseconds": 3002, "episode": 58, "trial": 18, "phase": "training", "completion_percentage": 19, "episode_status": "Off track"}, {"reward_score": 114, "metric_time": 460828, "start_time": 457688, "elapsed_time_in_milliseconds": 3140, "episode": 59, "trial": 19, "phase": "training", "completion_percentage": 19, "episode_status": "Off track"}, {"reward_score": 256, "metric_time": 466626, "start_time": 460886, "elapsed_time_in_milliseconds": 5740, "episode": 60, "trial": 20, "phase": "training", "completion_percentage": 37, "episode_status": "Off track"}, {"reward_score": 209, "metric_time": 471948, "start_time": 466746, "elapsed_time_in_milliseconds": 5202, "episode": 60, "trial": 20, "phase": "evaluation", "completion_percentage": 34, "episode_status": "Off track"}, {"reward_score": 119, "metric_time": 474957, "start_time": 472018, "elapsed_time_in_milliseconds": 2939, "episode": 60, "trial": 20, "phase": "evaluation", "completion_percentage": 19, "episode_status": "Off track"}, {"reward_score": 137, "metric_time": 478230, "start_time": 475035, "elapsed_time_in_milliseconds": 3195, "episode": 60, "trial": 20, "phase": "evaluation", "completion_percentage": 18, "episode_status": "Off track"}, {"reward_score": 193, "metric_time": 483162, "start_time": 478293, "elapsed_time_in_milliseconds": 4869, "episode": 60, "trial": 20, "phase": "evaluation", "completion_percentage": 29, "episode_status": "Off track"}, {"reward_score": 192, "metric_time": 488094, "start_time": 483222, "elapsed_time_in_milliseconds": 4872, "episode": 60, "trial": 20, "phase": "evaluation", "completion_percentage": 29, "episode_status": "Off track"}, {"reward_score": 525, "metric_time": 499363, "start_time": 488168, "elapsed_time_in_milliseconds": 11195, "episode": 61, "trial": 1, "phase": "training", "completion_percentage": 73, "episode_status": "Off track"}, {"reward_score": 133, "metric_time": 502827, "start_time": 499429, "elapsed_time_in_milliseconds": 3398, "episode": 62, "trial": 2, "phase": "training", "completion_percentage": 19, "episode_status": "Off track"}, {"reward_score": 82, "metric_time": 504887, "start_time": 502894, "elapsed_time_in_milliseconds": 1993, "episode": 63, "trial": 3, "phase": "training", "completion_percentage": 9, "episode_status": "Off track"}, {"reward_score": 779, "metric_time": 519961, "start_time": 504952, "elapsed_time_in_milliseconds": 15009, "episode": 64, "trial": 4, "phase": "training", "completion_percentage": 100, "episode_status": "Lap complete"}, {"reward_score": 253, "metric_time": 525966, "start_time": 520014, "elapsed_time_in_milliseconds": 5952, "episode": 65, "trial": 5, "phase": "training", "completion_percentage": 43, "episode_status": "Off track"}, {"reward_score": 506, "metric_time": 537024, "start_time": 526027, "elapsed_time_in_milliseconds": 10997, "episode": 66, "trial": 6, "phase": "training", "completion_percentage": 76, "episode_status": "Off track"}, {"reward_score": 289, "metric_time": 543358, "start_time": 537092, "elapsed_time_in_milliseconds": 6266, "episode": 67, "trial": 7, "phase": "training", "completion_percentage": 40, "episode_status": "Off track"}, {"reward_score": 251, "metric_time": 549408, "start_time": 543423, "elapsed_time_in_milliseconds": 5985, "episode": 68, "trial": 8, "phase": "training", "completion_percentage": 36, "episode_status": "Off track"}, {"reward_score": 619, "metric_time": 561959, "start_time": 549488, "elapsed_time_in_milliseconds": 12471, "episode": 69, "trial": 9, "phase": "training", "completion_percentage": 81, "episode_status": "Off track"}, {"reward_score": 531, "metric_time": 573359, "start_time": 562020, "elapsed_time_in_milliseconds": 11339, "episode": 70, "trial": 10, "phase": "training", "completion_percentage": 70, "episode_status": "Off track"}, {"reward_score": 111, "metric_time": 576154, "start_time": 573423, "elapsed_time_in_milliseconds": 2731, "episode": 71, "trial": 11, "phase": "training", "completion_percentage": 16, "episode_status": "Off track"}, {"reward_score": 144, "metric_time": 579886, "start_time": 576226, "elapsed_time_in_milliseconds": 3660, "episode": 72, "trial": 12, "phase": "training", "completion_percentage": 23, "episode_status": "Off track"}, {"reward_score": 453, "metric_time": 590494, "start_time": 579962, "elapsed_time_in_milliseconds": 10532, "episode": 73, "trial": 13, "phase": "training", "completion_percentage": 69, "episode_status": "Off track"}, {"reward_score": 863, "metric_time": 606695, "start_time": 590562, "elapsed_time_in_milliseconds": 16133, "episode": 74, "trial": 14, "phase": "training", "completion_percentage": 100, "episode_status": "Lap complete"}, {"reward_score": 181, "metric_time": 610889, "start_time": 606758, "elapsed_time_in_milliseconds": 4131, "episode": 75, "trial": 15, "phase": "training", "completion_percentage": 27, "episode_status": "Off track"}, {"reward_score": 521, "metric_time": 621158, "start_time": 610959, "elapsed_time_in_milliseconds": 10199, "episode": 76, "trial": 16, "phase": "training", "completion_percentage": 73, "episode_status": "Off track"}, {"reward_score": 320, "metric_time": 629010, "start_time": 621218, "elapsed_time_in_milliseconds": 7792, "episode": 77, "trial": 17, "phase": "training", "completion_percentage": 45, "episode_status": "Off track"}, {"reward_score": 818, "metric_time": 644563, "start_time": 629081, "elapsed_time_in_milliseconds": 15482, "episode": 78, "trial": 18, "phase": "training", "completion_percentage": 100, "episode_status": "Lap complete"}, {"reward_score": 289, "metric_time": 651099, "start_time": 644617, "elapsed_time_in_milliseconds": 6482, "episode": 79, "trial": 19, "phase": "training", "completion_percentage": 39, "episode_status": "Off track"}, {"reward_score": 186, "metric_time": 655352, "start_time": 651156, "elapsed_time_in_milliseconds": 4196, "episode": 80, "trial": 20, "phase": "training", "completion_percentage": 23, "episode_status": "Off track"}, {"reward_score": 136, "metric_time": 659149, "start_time": 655491, "elapsed_time_in_milliseconds": 3658, "episode": 80, "trial": 20, "phase": "evaluation", "completion_percentage": 20, "episode_status": "Off track"}, {"reward_score": 125, "metric_time": 662487, "start_time": 659225, "elapsed_time_in_milliseconds": 3262, "episode": 80, "trial": 20, "phase": "evaluation", "completion_percentage": 22, "episode_status": "Off track"}, {"reward_score": 68, "metric_time": 664564, "start_time": 662549, "elapsed_time_in_milliseconds": 2015, "episode": 80, "trial": 20, "phase": "evaluation", "completion_percentage": 11, "episode_status": "Off track"}, {"reward_score": 185, "metric_time": 669628, "start_time": 664629, "elapsed_time_in_milliseconds": 4999, "episode": 80, "trial": 20, "phase": "evaluation", "completion_percentage": 29, "episode_status": "Off track"}, {"reward_score": 798, "metric_time": 684489, "start_time": 669696, "elapsed_time_in_milliseconds": 14793, "episode": 80, "trial": 20, "phase": "evaluation", "completion_percentage": 100, "episode_status": "Lap complete"}, {"reward_score": 428, "metric_time": 694162, "start_time": 684552, "elapsed_time_in_milliseconds": 9610, "episode": 81, "trial": 1, "phase": "training", "completion_percentage": 63, "episode_status": "Off track"}, {"reward_score": 241, "metric_time": 699961, "start_time": 694224, "elapsed_time_in_milliseconds": 5737, "episode": 82, "trial": 2, "phase": "training", "completion_percentage": 34, "episode_status": "Off track"}, {"reward_score": 235, "metric_time": 705004, "start_time": 700028, "elapsed_time_in_milliseconds": 4976, "episode": 83, "trial": 3, "phase": "training", "completion_percentage": 19, "episode_status": "Reversed"}, {"reward_score": 353, "metric_time": 712624, "start_time": 705084, "elapsed_time_in_milliseconds": 7540, "episode": 84, "trial": 4, "phase": "training", "completion_percentage": 50, "episode_status": "Off track"}, {"reward_score": 664, "metric_time": 726431, "start_time": 712685, "elapsed_time_in_milliseconds": 13746, "episode": 85, "trial": 5, "phase": "training", "completion_percentage": 88, "episode_status": "Off track"}, {"reward_score": 50, "metric_time": 727825, "start_time": 726484, "elapsed_time_in_milliseconds": 1341, "episode": 86, "trial": 6, "phase": "training", "completion_percentage": 5, "episode_status": "Off track"}, {"reward_score": 276, "metric_time": 735161, "start_time": 727890, "elapsed_time_in_milliseconds": 7271, "episode": 87, "trial": 7, "phase": "training", "completion_percentage": 41, "episode_status": "Off track"}, {"reward_score": 485, "metric_time": 745021, "start_time": 735224, "elapsed_time_in_milliseconds": 9797, "episode": 88, "trial": 8, "phase": "training", "completion_percentage": 68, "episode_status": "Off track"}, {"reward_score": 490, "metric_time": 755629, "start_time": 745091, "elapsed_time_in_milliseconds": 10538, "episode": 89, "trial": 9, "phase": "training", "completion_percentage": 66, "episode_status": "Off track"}, {"reward_score": 436, "metric_time": 765159, "start_time": 755695, "elapsed_time_in_milliseconds": 9464, "episode": 90, "trial": 10, "phase": "training", "completion_percentage": 58, "episode_status": "Off track"}, {"reward_score": 400, "metric_time": 774225, "start_time": 765228, "elapsed_time_in_milliseconds": 8997, "episode": 91, "trial": 11, "phase": "training", "completion_percentage": 57, "episode_status": "Off track"}, {"reward_score": 350, "metric_time": 782760, "start_time": 774294, "elapsed_time_in_milliseconds": 8466, "episode": 92, "trial": 12, "phase": "training", "completion_percentage": 56, "episode_status": "Off track"}, {"reward_score": 393, "metric_time": 790830, "start_time": 782827, "elapsed_time_in_milliseconds": 8003, "episode": 93, "trial": 13, "phase": "training", "completion_percentage": 51, "episode_status": "Off track"}, {"reward_score": 516, "metric_time": 802092, "start_time": 790896, "elapsed_time_in_milliseconds": 11196, "episode": 94, "trial": 14, "phase": "training", "completion_percentage": 68, "episode_status": "Off track"}, {"reward_score": 552, "metric_time": 813367, "start_time": 802158, "elapsed_time_in_milliseconds": 11209, "episode": 95, "trial": 15, "phase": "training", "completion_percentage": 74, "episode_status": "Off track"}, {"reward_score": 813, "metric_time": 828364, "start_time": 813423, "elapsed_time_in_milliseconds": 14941, "episode": 96, "trial": 16, "phase": "training", "completion_percentage": 100, "episode_status": "Lap complete"}, {"reward_score": 347, "metric_time": 835560, "start_time": 828423, "elapsed_time_in_milliseconds": 7137, "episode": 97, "trial": 17, "phase": "training", "completion_percentage": 47, "episode_status": "Off track"}, {"reward_score": 370, "metric_time": 843562, "start_time": 835618, "elapsed_time_in_milliseconds": 7944, "episode": 98, "trial": 18, "phase": "training", "completion_percentage": 51, "episode_status": "Off track"}, {"reward_score": 154, "metric_time": 847362, "start_time": 843625, "elapsed_time_in_milliseconds": 3737, "episode": 99, "trial": 19, "phase": "training", "completion_percentage": 19, "episode_status": "Off track"}, {"reward_score": 239, "metric_time": 852824, "start_time": 847437, "elapsed_time_in_milliseconds": 5387, "episode": 100, "trial": 20, "phase": "training", "completion_percentage": 37, "episode_status": "Off track"}, {"reward_score": 102, "metric_time": 855897, "start_time": 852948, "elapsed_time_in_milliseconds": 2949, "episode": 100, "trial": 20, "phase": "evaluation", "completion_percentage": 19, "episode_status": "Off track"}, {"reward_score": 849, "metric_time": 871417, "start_time": 855961, "elapsed_time_in_milliseconds": 15456, "episode": 100, "trial": 20, "phase": "evaluation", "completion_percentage": 100, "episode_status": "Lap complete"}, {"reward_score": 250, "metric_time": 877354, "start_time": 871489, "elapsed_time_in_milliseconds": 5865, "episode": 100, "trial": 20, "phase": "evaluation", "completion_percentage": 39, "episode_status": "Off track"}, {"reward_score": 265, "metric_time": 883491, "start_time": 877417, "elapsed_time_in_milliseconds": 6074, "episode": 100, "trial": 20, "phase": "evaluation", "completion_percentage": 39, "episode_status": "Off track"}, {"reward_score": 167, "metric_time": 887697, "start_time": 883560, "elapsed_time_in_milliseconds": 4137, "episode": 100, "trial": 20, "phase": "evaluation", "completion_percentage": 25, "episode_status": "Off track"}, {"reward_score": 564, "metric_time": 898828, "start_time": 887755, "elapsed_time_in_milliseconds": 11073, "episode": 101, "trial": 1, "phase": "training", "completion_percentage": 71, "episode_status": "Off track"}, {"reward_score": 181, "metric_time": 903291, "start_time": 898891, "elapsed_time_in_milliseconds": 4400, "episode": 102, "trial": 2, "phase": "training", "completion_percentage": 28, "episode_status": "Off track"}, {"reward_score": 83, "metric_time": 905567, "start_time": 903360, "elapsed_time_in_milliseconds": 2207, "episode": 103, "trial": 3, "phase": "training", "completion_percentage": 14, "episode_status": "Off track"}, {"reward_score": 312, "metric_time": 912626, "start_time": 905623, "elapsed_time_in_milliseconds": 7003, "episode": 104, "trial": 4, "phase": "training", "completion_percentage": 49, "episode_status": "Off track"}, {"reward_score": 77, "metric_time": 914625, "start_time": 912695, "elapsed_time_in_milliseconds": 1930, "episode": 105, "trial": 5, "phase": "training", "completion_percentage": 9, "episode_status": "Off track"}, {"reward_score": 708, "metric_time": 928360, "start_time": 914689, "elapsed_time_in_milliseconds": 13671, "episode": 106, "trial": 6, "phase": "training", "completion_percentage": 87, "episode_status": "Off track"}, {"reward_score": 291, "metric_time": 935031, "start_time": 928429, "elapsed_time_in_milliseconds": 6602, "episode": 107, "trial": 7, "phase": "training", "completion_percentage": 42, "episode_status": "Off track"}, {"reward_score": 291, "metric_time": 942219, "start_time": 935090, "elapsed_time_in_milliseconds": 7129, "episode": 108, "trial": 8, "phase": "training", "completion_percentage": 44, "episode_status": "Off track"}, {"reward_score": 292, "metric_time": 948630, "start_time": 942282, "elapsed_time_in_milliseconds": 6348, "episode": 109, "trial": 9, "phase": "training", "completion_percentage": 34, "episode_status": "Off track"}, {"reward_score": 679, "metric_time": 962166, "start_time": 948693, "elapsed_time_in_milliseconds": 13473, "episode": 110, "trial": 10, "phase": "training", "completion_percentage": 85, "episode_status": "Off track"}, {"reward_score": 655, "metric_time": 975426, "start_time": 962230, "elapsed_time_in_milliseconds": 13196, "episode": 111, "trial": 11, "phase": "training", "completion_percentage": 84, "episode_status": "Off track"}, {"reward_score": 561, "metric_time": 986486, "start_time": 975493, "elapsed_time_in_milliseconds": 10993, "episode": 112, "trial": 12, "phase": "training", "completion_percentage": 77, "episode_status": "Off track"}, {"reward_score": 574, "metric_time": 998094, "start_time": 986562, "elapsed_time_in_milliseconds": 11532, "episode": 113, "trial": 13, "phase": "training", "completion_percentage": 68, "episode_status": "Off track"}, {"reward_score": 204, "metric_time": 1002890, "start_time": 998153, "elapsed_time_in_milliseconds": 4737, "episode": 114, "trial": 14, "phase": "training", "completion_percentage": 31, "episode_status": "Off track"}, {"reward_score": 264, "metric_time": 1008767, "start_time": 1002950, "elapsed_time_in_milliseconds": 5817, "episode": 115, "trial": 15, "phase": "training", "completion_percentage": 37, "episode_status": "Off track"}, {"reward_score": 503, "metric_time": 1019765, "start_time": 1008821, "elapsed_time_in_milliseconds": 10944, "episode": 116, "trial": 16, "phase": "training", "completion_percentage": 60, "episode_status": "Off track"}, {"reward_score": 795, "metric_time": 1035031, "start_time": 1019819, "elapsed_time_in_milliseconds": 15212, "episode": 117, "trial": 17, "phase": "training", "completion_percentage": 100, "episode_status": "Lap complete"}, {"reward_score": 368, "metric_time": 1042832, "start_time": 1035086, "elapsed_time_in_milliseconds": 7746, "episode": 118, "trial": 18, "phase": "training", "completion_percentage": 51, "episode_status": "Off track"}, {"reward_score": 183, "metric_time": 1047155, "start_time": 1042896, "elapsed_time_in_milliseconds": 4259, "episode": 119, "trial": 19, "phase": "training", "completion_percentage": 21, "episode_status": "Off track"}, {"reward_score": 848, "metric_time": 1063029, "start_time": 1047233, "elapsed_time_in_milliseconds": 15796, "episode": 120, "trial": 20, "phase": "training", "completion_percentage": 100, "episode_status": "Lap complete"}, {"reward_score": 273, "metric_time": 1069160, "start_time": 1063153, "elapsed_time_in_milliseconds": 6007, "episode": 120, "trial": 20, "phase": "evaluation", "completion_percentage": 43, "episode_status": "Off track"}, {"reward_score": 183, "metric_time": 1074297, "start_time": 1069229, "elapsed_time_in_milliseconds": 5068, "episode": 120, "trial": 20, "phase": "evaluation", "completion_percentage": 29, "episode_status": "Off track"}, {"reward_score": 213, "metric_time": 1079756, "start_time": 1074362, "elapsed_time_in_milliseconds": 5394, "episode": 120, "trial": 20, "phase": "evaluation", "completion_percentage": 34, "episode_status": "Off track"}, {"reward_score": 557, "metric_time": 1091473, "start_time": 1079823, "elapsed_time_in_milliseconds": 11650, "episode": 120, "trial": 20, "phase": "evaluation", "completion_percentage": 73, "episode_status": "Off track"}, {"reward_score": 171, "metric_time": 1095701, "start_time": 1091538, "elapsed_time_in_milliseconds": 4163, "episode": 120, "trial": 20, "phase": "evaluation", "completion_percentage": 26, "episode_status": "Off track"}, {"reward_score": 197, "metric_time": 1100752, "start_time": 1095764, "elapsed_time_in_milliseconds": 4988, "episode": 121, "trial": 1, "phase": "training", "completion_percentage": 32, "episode_status": "Off track"}, {"reward_score": 211, "metric_time": 1105629, "start_time": 1100816, "elapsed_time_in_milliseconds": 4813, "episode": 122, "trial": 2, "phase": "training", "completion_percentage": 24, "episode_status": "Off track"}, {"reward_score": 859, "metric_time": 1121561, "start_time": 1105696, "elapsed_time_in_milliseconds": 15865, "episode": 123, "trial": 3, "phase": "training", "completion_percentage": 100, "episode_status": "Lap complete"}, {"reward_score": 354, "metric_time": 1129827, "start_time": 1121625, "elapsed_time_in_milliseconds": 8202, "episode": 124, "trial": 4, "phase": "training", "completion_percentage": 56, "episode_status": "Off track"}, {"reward_score": 88, "metric_time": 1132217, "start_time": 1129895, "elapsed_time_in_milliseconds": 2322, "episode": 125, "trial": 5, "phase": "training", "completion_percentage": 13, "episode_status": "Off track"}, {"reward_score": 28, "metric_time": 1133425, "start_time": 1132289, "elapsed_time_in_milliseconds": 1136, "episode": 126, "trial": 6, "phase": "training", "completion_percentage": 7, "episode_status": "Off track"}, {"reward_score": 335, "metric_time": 1141368, "start_time": 1133486, "elapsed_time_in_milliseconds": 7882, "episode": 127, "trial": 7, "phase": "training", "completion_percentage": 51, "episode_status": "Off track"}, {"reward_score": 317, "metric_time": 1148367, "start_time": 1141430, "elapsed_time_in_milliseconds": 6937, "episode": 128, "trial": 8, "phase": "training", "completion_percentage": 41, "episode_status": "Off track"}, {"reward_score": 820, "metric_time": 1163559, "start_time": 1148420, "elapsed_time_in_milliseconds": 15139, "episode": 129, "trial": 9, "phase": "training", "completion_percentage": 100, "episode_status": "Lap complete"}, {"reward_score": 637, "metric_time": 1176832, "start_time": 1163620, "elapsed_time_in_milliseconds": 13212, "episode": 130, "trial": 10, "phase": "training", "completion_percentage": 85, "episode_status": "Off track"}, {"reward_score": 151, "metric_time": 1180697, "start_time": 1176886, "elapsed_time_in_milliseconds": 3811, "episode": 131, "trial": 11, "phase": "training", "completion_percentage": 22, "episode_status": "Off track"}, {"reward_score": 347, "metric_time": 1188894, "start_time": 1180759, "elapsed_time_in_milliseconds": 8135, "episode": 132, "trial": 12, "phase": "training", "completion_percentage": 53, "episode_status": "Off track"}, {"reward_score": 101, "metric_time": 1191495, "start_time": 1188956, "elapsed_time_in_milliseconds": 2539, "episode": 133, "trial": 13, "phase": "training", "completion_percentage": 14, "episode_status": "Off track"}, {"reward_score": 853, "metric_time": 1207289, "start_time": 1191553, "elapsed_time_in_milliseconds": 15736, "episode": 134, "trial": 14, "phase": "training", "completion_percentage": 100, "episode_status": "Lap complete"}, {"reward_score": 510, "metric_time": 1217823, "start_time": 1207351, "elapsed_time_in_milliseconds": 10472, "episode": 135, "trial": 15, "phase": "training", "completion_percentage": 68, "episode_status": "Off track"}, {"reward_score": 837, "metric_time": 1232955, "start_time": 1217883, "elapsed_time_in_milliseconds": 15072, "episode": 136, "trial": 16, "phase": "training", "completion_percentage": 100, "episode_status": "Lap complete"}, {"reward_score": 311, "metric_time": 1240095, "start_time": 1233026, "elapsed_time_in_milliseconds": 7069, "episode": 137, "trial": 17, "phase": "training", "completion_percentage": 41, "episode_status": "Off track"}, {"reward_score": 162, "metric_time": 1244025, "start_time": 1240158, "elapsed_time_in_milliseconds": 3867, "episode": 138, "trial": 18, "phase": "training", "completion_percentage": 23, "episode_status": "Off track"}, {"reward_score": 243, "metric_time": 1250352, "start_time": 1244087, "elapsed_time_in_milliseconds": 6265, "episode": 139, "trial": 19, "phase": "training", "completion_percentage": 43, "episode_status": "Off track"}, {"reward_score": 223, "metric_time": 1256230, "start_time": 1250423, "elapsed_time_in_milliseconds": 5807, "episode": 140, "trial": 20, "phase": "training", "completion_percentage": 35, "episode_status": "Off track"}, {"reward_score": 247, "metric_time": 1262161, "start_time": 1256360, "elapsed_time_in_milliseconds": 5801, "episode": 140, "trial": 20, "phase": "evaluation", "completion_percentage": 36, "episode_status": "Off track"}, {"reward_score": 214, "metric_time": 1267032, "start_time": 1262215, "elapsed_time_in_milliseconds": 4817, "episode": 140, "trial": 20, "phase": "evaluation", "completion_percentage": 28, "episode_status": "Off track"}, {"reward_score": 685, "metric_time": 1280407, "start_time": 1267087, "elapsed_time_in_milliseconds": 13320, "episode": 140, "trial": 20, "phase": "evaluation", "completion_percentage": 84, "episode_status": "Off track"}, {"reward_score": 220, "metric_time": 1285496, "start_time": 1280468, "elapsed_time_in_milliseconds": 5028, "episode": 140, "trial": 20, "phase": "evaluation", "completion_percentage": 30, "episode_status": "Off track"}, {"reward_score": 837, "metric_time": 1300964, "start_time": 1285556, "elapsed_time_in_milliseconds": 15408, "episode": 140, "trial": 20, "phase": "evaluation", "completion_percentage": 100, "episode_status": "Lap complete"}, {"reward_score": 298, "metric_time": 1307969, "start_time": 1301017, "elapsed_time_in_milliseconds": 6952, "episode": 141, "trial": 1, "phase": "training", "completion_percentage": 40, "episode_status": "Off track"}, {"reward_score": 816, "metric_time": 1323156, "start_time": 1308027, "elapsed_time_in_milliseconds": 15129, "episode": 142, "trial": 2, "phase": "training", "completion_percentage": 100, "episode_status": "Lap complete"}, {"reward_score": 123, "metric_time": 1326164, "start_time": 1323224, "elapsed_time_in_milliseconds": 2940, "episode": 143, "trial": 3, "phase": "training", "completion_percentage": 19, "episode_status": "Off track"}, {"reward_score": 851, "metric_time": 1341693, "start_time": 1326214, "elapsed_time_in_milliseconds": 15479, "episode": 144, "trial": 4, "phase": "training", "completion_percentage": 100, "episode_status": "Lap complete"}, {"reward_score": 793, "metric_time": 1356889, "start_time": 1341757, "elapsed_time_in_milliseconds": 15132, "episode": 145, "trial": 5, "phase": "training", "completion_percentage": 100, "episode_status": "Lap complete"}, {"reward_score": 812, "metric_time": 1372419, "start_time": 1356953, "elapsed_time_in_milliseconds": 15466, "episode": 146, "trial": 6, "phase": "training", "completion_percentage": 97, "episode_status": "Off track"}, {"reward_score": 298, "metric_time": 1379638, "start_time": 1372486, "elapsed_time_in_milliseconds": 7152, "episode": 147, "trial": 7, "phase": "training", "completion_percentage": 41, "episode_status": "Off track"}, {"reward_score": 466, "metric_time": 1389430, "start_time": 1379686, "elapsed_time_in_milliseconds": 9744, "episode": 148, "trial": 8, "phase": "training", "completion_percentage": 61, "episode_status": "Off track"}, {"reward_score": 745, "metric_time": 1404153, "start_time": 1389482, "elapsed_time_in_milliseconds": 14671, "episode": 149, "trial": 9, "phase": "training", "completion_percentage": 100, "episode_status": "Lap complete"}, {"reward_score": 625, "metric_time": 1417361, "start_time": 1404229, "elapsed_time_in_milliseconds": 13132, "episode": 150, "trial": 10, "phase": "training", "completion_percentage": 80, "episode_status": "Off track"}, {"reward_score": 535, "metric_time": 1428696, "start_time": 1417425, "elapsed_time_in_milliseconds": 11271, "episode": 151, "trial": 11, "phase": "training", "completion_percentage": 71, "episode_status": "Off track"}, {"reward_score": 125, "metric_time": 1432101, "start_time": 1428758, "elapsed_time_in_milliseconds": 3343, "episode": 152, "trial": 12, "phase": "training", "completion_percentage": 20, "episode_status": "Off track"}, {"reward_score": 337, "metric_time": 1439900, "start_time": 1432160, "elapsed_time_in_milliseconds": 7740, "episode": 153, "trial": 13, "phase": "training", "completion_percentage": 48, "episode_status": "Off track"}, {"reward_score": 60, "metric_time": 1441694, "start_time": 1439957, "elapsed_time_in_milliseconds": 1737, "episode": 154, "trial": 14, "phase": "training", "completion_percentage": 9, "episode_status": "Off track"}, {"reward_score": 830, "metric_time": 1457296, "start_time": 1441752, "elapsed_time_in_milliseconds": 15544, "episode": 155, "trial": 15, "phase": "training", "completion_percentage": 100, "episode_status": "Lap complete"}, {"reward_score": 821, "metric_time": 1472291, "start_time": 1457357, "elapsed_time_in_milliseconds": 14934, "episode": 156, "trial": 16, "phase": "training", "completion_percentage": 100, "episode_status": "Lap complete"}, {"reward_score": 389, "metric_time": 1480954, "start_time": 1472358, "elapsed_time_in_milliseconds": 8596, "episode": 157, "trial": 17, "phase": "training", "completion_percentage": 49, "episode_status": "Off track"}, {"reward_score": 66, "metric_time": 1482894, "start_time": 1481028, "elapsed_time_in_milliseconds": 1866, "episode": 158, "trial": 18, "phase": "training", "completion_percentage": 11, "episode_status": "Off track"}, {"reward_score": 726, "metric_time": 1497542, "start_time": 1482953, "elapsed_time_in_milliseconds": 14589, "episode": 159, "trial": 19, "phase": "training", "completion_percentage": 100, "episode_status": "Lap complete"}, {"reward_score": 345, "metric_time": 1504964, "start_time": 1497622, "elapsed_time_in_milliseconds": 7342, "episode": 160, "trial": 20, "phase": "training", "completion_percentage": 46, "episode_status": "Off track"}, {"reward_score": 727, "metric_time": 1519102, "start_time": 1505094, "elapsed_time_in_milliseconds": 14008, "episode": 160, "trial": 20, "phase": "evaluation", "completion_percentage": 100, "episode_status": "Lap complete"}, {"reward_score": 759, "metric_time": 1533354, "start_time": 1519151, "elapsed_time_in_milliseconds": 14203, "episode": 160, "trial": 20, "phase": "evaluation", "completion_percentage": 100, "episode_status": "Lap complete"}, {"reward_score": 204, "metric_time": 1538623, "start_time": 1533430, "elapsed_time_in_milliseconds": 5193, "episode": 160, "trial": 20, "phase": "evaluation", "completion_percentage": 35, "episode_status": "Off track"}, {"reward_score": 280, "metric_time": 1545234, "start_time": 1538696, "elapsed_time_in_milliseconds": 6538, "episode": 160, "trial": 20, "phase": "evaluation", "completion_percentage": 44, "episode_status": "Off track"}, {"reward_score": 157, "metric_time": 1549170, "start_time": 1545292, "elapsed_time_in_milliseconds": 3878, "episode": 160, "trial": 20, "phase": "evaluation", "completion_percentage": 22, "episode_status": "Off track"}, {"reward_score": 179, "metric_time": 1553835, "start_time": 1549228, "elapsed_time_in_milliseconds": 4607, "episode": 161, "trial": 1, "phase": "training", "completion_percentage": 28, "episode_status": "Off track"}, {"reward_score": 181, "metric_time": 1557953, "start_time": 1553897, "elapsed_time_in_milliseconds": 4056, "episode": 162, "trial": 2, "phase": "training", "completion_percentage": 22, "episode_status": "Off track"}, {"reward_score": 147, "metric_time": 1561886, "start_time": 1558017, "elapsed_time_in_milliseconds": 3869, "episode": 163, "trial": 3, "phase": "training", "completion_percentage": 24, "episode_status": "Off track"}, {"reward_score": 344, "metric_time": 1569365, "start_time": 1561956, "elapsed_time_in_milliseconds": 7409, "episode": 164, "trial": 4, "phase": "training", "completion_percentage": 49, "episode_status": "Off track"}, {"reward_score": 869, "metric_time": 1585030, "start_time": 1569428, "elapsed_time_in_milliseconds": 15602, "episode": 165, "trial": 5, "phase": "training", "completion_percentage": 100, "episode_status": "Lap complete"}, {"reward_score": 331, "metric_time": 1592160, "start_time": 1585091, "elapsed_time_in_milliseconds": 7069, "episode": 166, "trial": 6, "phase": "training", "completion_percentage": 46, "episode_status": "Off track"}, {"reward_score": 304, "metric_time": 1598830, "start_time": 1592228, "elapsed_time_in_milliseconds": 6602, "episode": 167, "trial": 7, "phase": "training", "completion_percentage": 43, "episode_status": "Off track"}, {"reward_score": 730, "metric_time": 1613618, "start_time": 1598895, "elapsed_time_in_milliseconds": 14723, "episode": 168, "trial": 8, "phase": "training", "completion_percentage": 100, "episode_status": "Lap complete"}, {"reward_score": 720, "metric_time": 1627951, "start_time": 1613693, "elapsed_time_in_milliseconds": 14258, "episode": 169, "trial": 9, "phase": "training", "completion_percentage": 88, "episode_status": "Off track"}, {"reward_score": 492, "metric_time": 1638024, "start_time": 1628023, "elapsed_time_in_milliseconds": 10001, "episode": 170, "trial": 10, "phase": "training", "completion_percentage": 65, "episode_status": "Off track"}, {"reward_score": 571, "metric_time": 1650223, "start_time": 1638098, "elapsed_time_in_milliseconds": 12125, "episode": 171, "trial": 11, "phase": "training", "completion_percentage": 77, "episode_status": "Off track"}, {"reward_score": 549, "metric_time": 1661826, "start_time": 1650293, "elapsed_time_in_milliseconds": 11533, "episode": 172, "trial": 12, "phase": "training", "completion_percentage": 80, "episode_status": "Off track"}, {"reward_score": 378, "metric_time": 1670163, "start_time": 1661885, "elapsed_time_in_milliseconds": 8278, "episode": 173, "trial": 13, "phase": "training", "completion_percentage": 50, "episode_status": "Off track"}, {"reward_score": 330, "metric_time": 1677960, "start_time": 1670219, "elapsed_time_in_milliseconds": 7741, "episode": 174, "trial": 14, "phase": "training", "completion_percentage": 47, "episode_status": "Off track"}, {"reward_score": 452, "metric_time": 1688094, "start_time": 1678033, "elapsed_time_in_milliseconds": 10061, "episode": 175, "trial": 15, "phase": "training", "completion_percentage": 65, "episode_status": "Off track"}, {"reward_score": 135, "metric_time": 1691764, "start_time": 1688150, "elapsed_time_in_milliseconds": 3614, "episode": 176, "trial": 16, "phase": "training", "completion_percentage": 20, "episode_status": "Off track"}, {"reward_score": 317, "metric_time": 1698561, "start_time": 1691824, "elapsed_time_in_milliseconds": 6737, "episode": 177, "trial": 17, "phase": "training", "completion_percentage": 39, "episode_status": "Off track"}, {"reward_score": 755, "metric_time": 1713153, "start_time": 1698634, "elapsed_time_in_milliseconds": 14519, "episode": 178, "trial": 18, "phase": "training", "completion_percentage": 100, "episode_status": "Lap complete"}, {"reward_score": 226, "metric_time": 1718099, "start_time": 1713214, "elapsed_time_in_milliseconds": 4885, "episode": 179, "trial": 19, "phase": "training", "completion_percentage": 30, "episode_status": "Off track"}, {"reward_score": 200, "metric_time": 1722752, "start_time": 1718158, "elapsed_time_in_milliseconds": 4594, "episode": 180, "trial": 20, "phase": "training", "completion_percentage": 27, "episode_status": "Off track"}, {"reward_score": 191, "metric_time": 1727752, "start_time": 1722884, "elapsed_time_in_milliseconds": 4868, "episode": 180, "trial": 20, "phase": "evaluation", "completion_percentage": 29, "episode_status": "Off track"}, {"reward_score": 202, "metric_time": 1732545, "start_time": 1727818, "elapsed_time_in_milliseconds": 4727, "episode": 180, "trial": 20, "phase": "evaluation", "completion_percentage": 17, "episode_status": "Reversed"}, {"reward_score": 152, "metric_time": 1737296, "start_time": 1732607, "elapsed_time_in_milliseconds": 4689, "episode": 180, "trial": 20, "phase": "evaluation", "completion_percentage": 29, "episode_status": "Off track"}, {"reward_score": 796, "metric_time": 1751890, "start_time": 1737360, "elapsed_time_in_milliseconds": 14530, "episode": 180, "trial": 20, "phase": "evaluation", "completion_percentage": 100, "episode_status": "Lap complete"}, {"reward_score": 788, "metric_time": 1766951, "start_time": 1751957, "elapsed_time_in_milliseconds": 14994, "episode": 180, "trial": 20, "phase": "evaluation", "completion_percentage": 100, "episode_status": "Lap complete"}], "version": 2.0, "best_model_metric": "progress"}